[
 {
   "FirstName": "DeVaughn",
   "LastName": "Akoon-Purcell",
   "Position": 2,
   "Age": 25,
   "CollegeYear": 4,
   "Height": 78,
   "DisplayHeight": "6-6",
   "Weight": 201,
   "College": "Eastern Oklahoma State College",
   "Consistency": 60,
   "Greed": 27,
   "Loyalty": 56,
   "PlayForWinner": 21,
   "PlayingTime": 45,
   "Personality": 42,
   "Durability": 45,
   "WorkEthic": 56,
   "DunkRate": 29,
   "RARate": 7,
   "DriveKick": 99,
   "DriveShot": 35,
   "PostUp": 67,
   "PullUp": 20,
   "CS": 33,
   "Pass": 0,
   "LocATB": 32,
   "LocCorner": 73,
   "LocMidrange": 40,
   "LocPaint": 61,
   "FG_RA": 66,
   "FG_ITP": 66,
   "FG_MID": 34,
   "FG_COR": 32,
   "FG_ATB": 80,
   "FT": 0,
   "Scoring": 61,
   "Passing": 24,
   "Handling": 33,
   "OReb": 57,
   "DReb": 56,
   "Block": 43,
   "Steal": 47,
   "DrawFoul": 11,
   "Defender": 46,
   "Discipline": 71,
   "BballIQ": 58,
   "FG_RA_POT": 73,
   "FG_ITP_POT": 73,
   "FG_MID_POT": 41,
   "FG_COR_POT": 39,
   "FG_ATB_POT": 87,
   "FT_POT": 7,
   "Scoring_POT": 68,
   "Passing_POT": 31,
   "Handling_POT": 40,
   "OReb_POT": 64,
   "DReb_POT": 63,
   "Block_POT": 50,
   "Steal_POT": 54,
   "DrawFoul_POT": 18,
   "Defender_POT": 53,
   "Discipline_POT": 78,
   "BballIQ_POT": 65
 },
 {
   "FirstName": "Kostas",
   "LastName": "Antetokounmpo",
   "Position": 3,
   "Age": 18,
   "CollegeYear": 1,
   "Height": 82,
   "DisplayHeight": "6-10",
   "Weight": 195,
   "College": "Greece",
   "Consistency": 44,
   "Greed": 79,
   "Loyalty": 79,
   "PlayForWinner": 34,
   "PlayingTime": 42,
   "Personality": 61,
   "Durability": 66,
   "WorkEthic": 83,
   "DunkRate": 67,
   "RARate": 6,
   "DriveKick": 40,
   "DriveShot": 27,
   "PostUp": 30,
   "PullUp": 15,
   "CS": 35,
   "Pass": 35,
   "LocATB": 39,
   "LocCorner": 78,
   "LocMidrange": 31,
   "LocPaint": 52,
   "FG_RA": 65,
   "FG_ITP": 65,
   "FG_MID": 39,
   "FG_COR": 44,
   "FG_ATB": 69,
   "FT": 27,
   "Scoring": 45,
   "Passing": 28,
   "Handling": 35,
   "OReb": 49,
   "DReb": 73,
   "Block": 56,
   "Steal": 64,
   "DrawFoul": 7,
   "Defender": 60,
   "Discipline": 62,
   "BballIQ": 66,
   "FG_RA_POT": 72,
   "FG_ITP_POT": 72,
   "FG_MID_POT": 46,
   "FG_COR_POT": 51,
   "FG_ATB_POT": 76,
   "FT_POT": 34,
   "Scoring_POT": 52,
   "Passing_POT": 35,
   "Handling_POT": 42,
   "OReb_POT": 56,
   "DReb_POT": 80,
   "Block_POT": 63,
   "Steal_POT": 71,
   "DrawFoul_POT": 14,
   "Defender_POT": 67,
   "Discipline_POT": 69,
   "BballIQ_POT": 73
 },
 {
   "FirstName": "LiAngelo",
   "LastName": "Ball",
   "Position": 2,
   "Age": 20,
   "CollegeYear": 4,
   "Height": 77,
   "DisplayHeight": "6-5",
   "Weight": 230,
   "College": "JBA",
   "Consistency": 39,
   "Greed": 69,
   "Loyalty": 70,
   "PlayForWinner": 66,
   "PlayingTime": 53,
   "Personality": 60,
   "Durability": 74,
   "WorkEthic": 23,
   "DunkRate": 51,
   "RARate": 27,
   "DriveKick": 50,
   "DriveShot": 34,
   "PostUp": 67,
   "PullUp": 23,
   "CS": 33,
   "Pass": 0,
   "LocATB": 26,
   "LocCorner": 58,
   "LocMidrange": 32,
   "LocPaint": 60,
   "FG_RA": 57,
   "FG_ITP": 57,
   "FG_MID": 40,
   "FG_COR": 39,
   "FG_ATB": 87,
   "FT": 35,
   "Scoring": 43,
   "Passing": 45,
   "Handling": 61,
   "OReb": 38,
   "DReb": 56,
   "Block": 47,
   "Steal": 39,
   "DrawFoul": 4,
   "Defender": 34,
   "Discipline": 65,
   "BballIQ": 57,
   "FG_RA_POT": 64,
   "FG_ITP_POT": 64,
   "FG_MID_POT": 47,
   "FG_COR_POT": 46,
   "FG_ATB_POT": 94,
   "FT_POT": 42,
   "Scoring_POT": 50,
   "Passing_POT": 52,
   "Handling_POT": 68,
   "OReb_POT": 45,
   "DReb_POT": 63,
   "Block_POT": 54,
   "Steal_POT": 46,
   "DrawFoul_POT": 11,
   "Defender_POT": 41,
   "Discipline_POT": 72,
   "BballIQ_POT": 64
 },
 {
   "FirstName": "Leron",
   "LastName": "Black",
   "Position": 4,
   "Age": 23,
   "CollegeYear": 4,
   "Height": 79,
   "DisplayHeight": "6-7",
   "Weight": 230,
   "College": "Illinois",
   "Consistency": 87,
   "Greed": 92,
   "Loyalty": 78,
   "PlayForWinner": 80,
   "PlayingTime": 87,
   "Personality": 79,
   "Durability": 77,
   "WorkEthic": 92,
   "DunkRate": 85,
   "RARate": 32,
   "DriveKick": 24,
   "DriveShot": 39,
   "PostUp": 69,
   "PullUp": 50,
   "CS": 31,
   "Pass": 0,
   "LocATB": 24,
   "LocCorner": 57,
   "LocMidrange": 39,
   "LocPaint": 65,
   "FG_RA": 44,
   "FG_ITP": 44,
   "FG_MID": 37,
   "FG_COR": 35,
   "FG_ATB": 70,
   "FT": 27,
   "Scoring": 23,
   "Passing": 40,
   "Handling": 50,
   "OReb": 27,
   "DReb": 48,
   "Block": 27,
   "Steal": 54,
   "DrawFoul": 3,
   "Defender": 44,
   "Discipline": 62,
   "BballIQ": 73,
   "FG_RA_POT": 51,
   "FG_ITP_POT": 51,
   "FG_MID_POT": 44,
   "FG_COR_POT": 42,
   "FG_ATB_POT": 77,
   "FT_POT": 34,
   "Scoring_POT": 30,
   "Passing_POT": 47,
   "Handling_POT": 57,
   "OReb_POT": 34,
   "DReb_POT": 55,
   "Block_POT": 34,
   "Steal_POT": 61,
   "DrawFoul_POT": 10,
   "Defender_POT": 51,
   "Discipline_POT": 69,
   "BballIQ_POT": 80
 },
 {
   "FirstName": "Antonio",
   "LastName": "Blakeney",
   "Position": 1,
   "Age": 21,
   "CollegeYear": 3,
   "Height": 76,
   "DisplayHeight": "6-4",
   "Weight": 192,
   "College": "LSU",
   "Consistency": 41,
   "Greed": 63,
   "Loyalty": 55,
   "PlayForWinner": 27,
   "PlayingTime": 30,
   "Personality": 55,
   "Durability": 46,
   "WorkEthic": 31,
   "DunkRate": 42,
   "RARate": 21,
   "DriveKick": 84,
   "DriveShot": 33,
   "PostUp": 100,
   "PullUp": 0,
   "CS": 0,
   "Pass": 0,
   "LocATB": 16,
   "LocCorner": 38,
   "LocMidrange": 33,
   "LocPaint": 62,
   "FG_RA": 62,
   "FG_ITP": 62,
   "FG_MID": 28,
   "FG_COR": 35,
   "FG_ATB": 69,
   "FT": 37,
   "Scoring": 27,
   "Passing": 42,
   "Handling": 32,
   "OReb": 53,
   "DReb": 62,
   "Block": 42,
   "Steal": 58,
   "DrawFoul": 2,
   "Defender": 45,
   "Discipline": 50,
   "BballIQ": 48,
   "FG_RA_POT": 69,
   "FG_ITP_POT": 69,
   "FG_MID_POT": 35,
   "FG_COR_POT": 42,
   "FG_ATB_POT": 76,
   "FT_POT": 44,
   "Scoring_POT": 34,
   "Passing_POT": 49,
   "Handling_POT": 39,
   "OReb_POT": 60,
   "DReb_POT": 69,
   "Block_POT": 49,
   "Steal_POT": 65,
   "DrawFoul_POT": 9,
   "Defender_POT": 52,
   "Discipline_POT": 57,
   "BballIQ_POT": 55
 },
 {
   "FirstName": "Jonah",
   "LastName": "Bolden",
   "Position": 4,
   "Age": 22,
   "CollegeYear": 1,
   "Height": 82,
   "DisplayHeight": "6-10",
   "Weight": 220,
   "College": "UCLA",
   "Consistency": 33,
   "Greed": 14,
   "Loyalty": 80,
   "PlayForWinner": 69,
   "PlayingTime": 39,
   "Personality": 62,
   "Durability": 40,
   "WorkEthic": 66,
   "DunkRate": 70,
   "RARate": 9,
   "DriveKick": 44,
   "DriveShot": 25,
   "PostUp": 37,
   "PullUp": 5,
   "CS": 60,
   "Pass": 3,
   "LocATB": 40,
   "LocCorner": 68,
   "LocMidrange": 34,
   "LocPaint": 57,
   "FG_RA": 58,
   "FG_ITP": 58,
   "FG_MID": 36,
   "FG_COR": 37,
   "FG_ATB": 70,
   "FT": 5,
   "Scoring": 48,
   "Passing": 24,
   "Handling": 45,
   "OReb": 60,
   "DReb": 41,
   "Block": 42,
   "Steal": 36,
   "DrawFoul": 7,
   "Defender": 60,
   "Discipline": 78,
   "BballIQ": 38,
   "FG_RA_POT": 65,
   "FG_ITP_POT": 65,
   "FG_MID_POT": 43,
   "FG_COR_POT": 44,
   "FG_ATB_POT": 77,
   "FT_POT": 12,
   "Scoring_POT": 55,
   "Passing_POT": 31,
   "Handling_POT": 52,
   "OReb_POT": 67,
   "DReb_POT": 48,
   "Block_POT": 49,
   "Steal_POT": 43,
   "DrawFoul_POT": 14,
   "Defender_POT": 67,
   "Discipline_POT": 85,
   "BballIQ_POT": 45
 },
 {
   "FirstName": "Miles",
   "LastName": "Bridges",
   "Position": 3,
   "Age": 20,
   "CollegeYear": 1,
   "Height": 79,
   "DisplayHeight": "6-7",
   "Weight": 220,
   "College": "Michigan State",
   "Consistency": 42,
   "Greed": 87,
   "Loyalty": 39,
   "PlayForWinner": 24,
   "PlayingTime": 66,
   "Personality": 31,
   "Durability": 79,
   "WorkEthic": 20,
   "DunkRate": 75,
   "RARate": 23,
   "DriveKick": 61,
   "DriveShot": 27,
   "PostUp": 90,
   "PullUp": 44,
   "CS": 10,
   "Pass": 0,
   "LocATB": 36,
   "LocCorner": 54,
   "LocMidrange": 25,
   "LocPaint": 57,
   "FG_RA": 58,
   "FG_ITP": 58,
   "FG_MID": 43,
   "FG_COR": 41,
   "FG_ATB": 65,
   "FT": 36,
   "Scoring": 45,
   "Passing": 27,
   "Handling": 55,
   "OReb": 40,
   "DReb": 55,
   "Block": 45,
   "Steal": 35,
   "DrawFoul": 12,
   "Defender": 43,
   "Discipline": 74,
   "BballIQ": 67,
   "FG_RA_POT": 65,
   "FG_ITP_POT": 65,
   "FG_MID_POT": 50,
   "FG_COR_POT": 48,
   "FG_ATB_POT": 72,
   "FT_POT": 43,
   "Scoring_POT": 52,
   "Passing_POT": 34,
   "Handling_POT": 62,
   "OReb_POT": 47,
   "DReb_POT": 62,
   "Block_POT": 52,
   "Steal_POT": 42,
   "DrawFoul_POT": 19,
   "Defender_POT": 50,
   "Discipline_POT": 81,
   "BballIQ_POT": 74
 },
 {
   "FirstName": "Mikal",
   "LastName": "Bridges",
   "Position": 3,
   "Age": 22,
   "CollegeYear": 1,
   "Height": 79,
   "DisplayHeight": "6-7",
   "Weight": 210,
   "College": "Villanova",
   "Consistency": 77,
   "Greed": 90,
   "Loyalty": 69,
   "PlayForWinner": 61,
   "PlayingTime": 56,
   "Personality": 74,
   "Durability": 61,
   "WorkEthic": 77,
   "DunkRate": 70,
   "RARate": 11,
   "DriveKick": 69,
   "DriveShot": 33,
   "PostUp": 67,
   "PullUp": 35,
   "CS": 23,
   "Pass": 10,
   "LocATB": 33,
   "LocCorner": 67,
   "LocMidrange": 24,
   "LocPaint": 50,
   "FG_RA": 62,
   "FG_ITP": 62,
   "FG_MID": 34,
   "FG_COR": 35,
   "FG_ATB": 70,
   "FT": 0,
   "Scoring": 58,
   "Passing": 46,
   "Handling": 45,
   "OReb": 44,
   "DReb": 39,
   "Block": 59,
   "Steal": 35,
   "DrawFoul": 3,
   "Defender": 47,
   "Discipline": 19,
   "BballIQ": 61,
   "FG_RA_POT": 69,
   "FG_ITP_POT": 69,
   "FG_MID_POT": 41,
   "FG_COR_POT": 42,
   "FG_ATB_POT": 77,
   "FT_POT": 7,
   "Scoring_POT": 65,
   "Passing_POT": 53,
   "Handling_POT": 52,
   "OReb_POT": 51,
   "DReb_POT": 46,
   "Block_POT": 66,
   "Steal_POT": 42,
   "DrawFoul_POT": 10,
   "Defender_POT": 54,
   "Discipline_POT": 26,
   "BballIQ_POT": 68
 },
 {
   "FirstName": "Troy",
   "LastName": "Brown",
   "Position": 2,
   "Age": 19,
   "CollegeYear": 3,
   "Height": 79,
   "DisplayHeight": "6-7",
   "Weight": 215,
   "College": "Oregon",
   "Consistency": 66,
   "Greed": 34,
   "Loyalty": 31,
   "PlayForWinner": 42,
   "PlayingTime": 35,
   "Personality": 72,
   "Durability": 79,
   "WorkEthic": 68,
   "DunkRate": 43,
   "RARate": 6,
   "DriveKick": 78,
   "DriveShot": 33,
   "PostUp": 25,
   "PullUp": 36,
   "CS": 55,
   "Pass": 20,
   "LocATB": 40,
   "LocCorner": 67,
   "LocMidrange": 31,
   "LocPaint": 54,
   "FG_RA": 63,
   "FG_ITP": 63,
   "FG_MID": 33,
   "FG_COR": 41,
   "FG_ATB": 70,
   "FT": 35,
   "Scoring": 39,
   "Passing": 40,
   "Handling": 54,
   "OReb": 43,
   "DReb": 44,
   "Block": 34,
   "Steal": 52,
   "DrawFoul": 6,
   "Defender": 50,
   "Discipline": 65,
   "BballIQ": 39,
   "FG_RA_POT": 70,
   "FG_ITP_POT": 70,
   "FG_MID_POT": 40,
   "FG_COR_POT": 48,
   "FG_ATB_POT": 77,
   "FT_POT": 42,
   "Scoring_POT": 46,
   "Passing_POT": 47,
   "Handling_POT": 61,
   "OReb_POT": 50,
   "DReb_POT": 51,
   "Block_POT": 41,
   "Steal_POT": 59,
   "DrawFoul_POT": 13,
   "Defender_POT": 57,
   "Discipline_POT": 72,
   "BballIQ_POT": 46
 },
 {
   "FirstName": "Elijah",
   "LastName": "Bryant",
   "Position": 2,
   "Age": 23,
   "CollegeYear": 4,
   "Height": 77,
   "DisplayHeight": "6-5",
   "Weight": 210,
   "College": "BYU",
   "Consistency": 81,
   "Greed": 91,
   "Loyalty": 66,
   "PlayForWinner": 46,
   "PlayingTime": 84,
   "Personality": 31,
   "Durability": 45,
   "WorkEthic": 37,
   "DunkRate": 46,
   "RARate": 26,
   "DriveKick": 67,
   "DriveShot": 33,
   "PostUp": 77,
   "PullUp": 1,
   "CS": 23,
   "Pass": 0,
   "LocATB": 27,
   "LocCorner": 70,
   "LocMidrange": 40,
   "LocPaint": 57,
   "FG_RA": 51,
   "FG_ITP": 51,
   "FG_MID": 34,
   "FG_COR": 32,
   "FG_ATB": 68,
   "FT": 30,
   "Scoring": 37,
   "Passing": 38,
   "Handling": 41,
   "OReb": 43,
   "DReb": 38,
   "Block": 35,
   "Steal": 61,
   "DrawFoul": 2,
   "Defender": 44,
   "Discipline": 57,
   "BballIQ": 57,
   "FG_RA_POT": 58,
   "FG_ITP_POT": 58,
   "FG_MID_POT": 41,
   "FG_COR_POT": 39,
   "FG_ATB_POT": 75,
   "FT_POT": 37,
   "Scoring_POT": 44,
   "Passing_POT": 45,
   "Handling_POT": 48,
   "OReb_POT": 50,
   "DReb_POT": 45,
   "Block_POT": 42,
   "Steal_POT": 68,
   "DrawFoul_POT": 9,
   "Defender_POT": 51,
   "Discipline_POT": 64,
   "BballIQ_POT": 64
 },
 {
   "FirstName": "Antonius",
   "LastName": "Cleveland",
   "Position": 2,
   "Age": 22,
   "CollegeYear": 4,
   "Height": 78,
   "DisplayHeight": "6-6",
   "Weight": 195,
   "College": "Southeast Missouri State",
   "Consistency": 25,
   "Greed": 60,
   "Loyalty": 37,
   "PlayForWinner": 22,
   "PlayingTime": 30,
   "Personality": 30,
   "Durability": 36,
   "WorkEthic": 18,
   "DunkRate": 31,
   "RARate": 22,
   "DriveKick": 64,
   "DriveShot": 62,
   "PostUp": 78,
   "PullUp": 50,
   "CS": 22,
   "Pass": 0,
   "LocATB": 24,
   "LocCorner": 47,
   "LocMidrange": 24,
   "LocPaint": 67,
   "FG_RA": 44,
   "FG_ITP": 44,
   "FG_MID": 37,
   "FG_COR": 35,
   "FG_ATB": 70,
   "FT": 27,
   "Scoring": 23,
   "Passing": 40,
   "Handling": 50,
   "OReb": 27,
   "DReb": 48,
   "Block": 27,
   "Steal": 54,
   "DrawFoul": 3,
   "Defender": 44,
   "Discipline": 62,
   "BballIQ": 73,
   "FG_RA_POT": 51,
   "FG_ITP_POT": 51,
   "FG_MID_POT": 44,
   "FG_COR_POT": 42,
   "FG_ATB_POT": 77,
   "FT_POT": 34,
   "Scoring_POT": 30,
   "Passing_POT": 47,
   "Handling_POT": 57,
   "OReb_POT": 34,
   "DReb_POT": 55,
   "Block_POT": 34,
   "Steal_POT": 61,
   "DrawFoul_POT": 10,
   "Defender_POT": 51,
   "Discipline_POT": 69,
   "BballIQ_POT": 80
 },
 {
   "FirstName": "John",
   "LastName": "Collins",
   "Position": 4,
   "Age": 20,
   "CollegeYear": 4,
   "Height": 82,
   "DisplayHeight": "6-10",
   "Weight": 225,
   "College": "Wake Forest",
   "Consistency": 22,
   "Greed": 93,
   "Loyalty": 13,
   "PlayForWinner": 44,
   "PlayingTime": 31,
   "Personality": 37,
   "Durability": 40,
   "WorkEthic": 28,
   "DunkRate": 78,
   "RARate": 20,
   "DriveKick": 37,
   "DriveShot": 67,
   "PostUp": 76,
   "PullUp": 50,
   "CS": 24,
   "Pass": 0,
   "LocATB": 43,
   "LocCorner": 55,
   "LocMidrange": 36,
   "LocPaint": 64,
   "FG_RA": 58,
   "FG_ITP": 58,
   "FG_MID": 43,
   "FG_COR": 41,
   "FG_ATB": 65,
   "FT": 36,
   "Scoring": 45,
   "Passing": 27,
   "Handling": 55,
   "OReb": 40,
   "DReb": 55,
   "Block": 45,
   "Steal": 35,
   "DrawFoul": 12,
   "Defender": 43,
   "Discipline": 74,
   "BballIQ": 67,
   "FG_RA_POT": 65,
   "FG_ITP_POT": 65,
   "FG_MID_POT": 50,
   "FG_COR_POT": 48,
   "FG_ATB_POT": 72,
   "FT_POT": 43,
   "Scoring_POT": 52,
   "Passing_POT": 34,
   "Handling_POT": 62,
   "OReb_POT": 47,
   "DReb_POT": 62,
   "Block_POT": 52,
   "Steal_POT": 42,
   "DrawFoul_POT": 19,
   "Defender_POT": 50,
   "Discipline_POT": 81,
   "BballIQ_POT": 74
 },
 {
   "FirstName": "Petr",
   "LastName": "Cornelie",
   "Position": 4,
   "Age": 22,
   "CollegeYear": 1,
   "Height": 83,
   "DisplayHeight": "6-11",
   "Weight": 220,
   "College": "France",
   "Consistency": 31,
   "Greed": 95,
   "Loyalty": 30,
   "PlayForWinner": 55,
   "PlayingTime": 91,
   "Personality": 38,
   "Durability": 60,
   "WorkEthic": 44,
   "DunkRate": 30,
   "RARate": 17,
   "DriveKick": 13,
   "DriveShot": 31,
   "PostUp": 68,
   "PullUp": 30,
   "CS": 30,
   "Pass": 2,
   "LocATB": 37,
   "LocCorner": 64,
   "LocMidrange": 35,
   "LocPaint": 57,
   "FG_RA": 61,
   "FG_ITP": 61,
   "FG_MID": 37,
   "FG_COR": 36,
   "FG_ATB": 64,
   "FT": 17,
   "Scoring": 40,
   "Passing": 34,
   "Handling": 58,
   "OReb": 35,
   "DReb": 43,
   "Block": 28,
   "Steal": 58,
   "DrawFoul": 5,
   "Defender": 61,
   "Discipline": 67,
   "BballIQ": 45,
   "FG_RA_POT": 68,
   "FG_ITP_POT": 68,
   "FG_MID_POT": 44,
   "FG_COR_POT": 43,
   "FG_ATB_POT": 71,
   "FT_POT": 24,
   "Scoring_POT": 47,
   "Passing_POT": 41,
   "Handling_POT": 65,
   "OReb_POT": 42,
   "DReb_POT": 50,
   "Block_POT": 35,
   "Steal_POT": 65,
   "DrawFoul_POT": 12,
   "Defender_POT": 68,
   "Discipline_POT": 74,
   "BballIQ_POT": 52
 },
 {
   "FirstName": "Tyler",
   "LastName": "Davis",
   "Position": 5,
   "Age": 21,
   "CollegeYear": 4,
   "Height": 82,
   "DisplayHeight": "6-10",
   "Weight": 266,
   "College": "Texas A&M",
   "Consistency": 27,
   "Greed": 45,
   "Loyalty": 64,
   "PlayForWinner": 30,
   "PlayingTime": 23,
   "Personality": 61,
   "Durability": 48,
   "WorkEthic": 43,
   "DunkRate": 68,
   "RARate": 7,
   "DriveKick": 57,
   "DriveShot": 42,
   "PostUp": 76,
   "PullUp": 2,
   "CS": 24,
   "Pass": 0,
   "LocATB": 28,
   "LocCorner": 60,
   "LocMidrange": 29,
   "LocPaint": 50,
   "FG_RA": 41,
   "FG_ITP": 41,
   "FG_MID": 33,
   "FG_COR": 31,
   "FG_ATB": 84,
   "FT": 34,
   "Scoring": 44,
   "Passing": 37,
   "Handling": 31,
   "OReb": 33,
   "DReb": 48,
   "Block": 39,
   "Steal": 38,
   "DrawFoul": 13,
   "Defender": 47,
   "Discipline": 77,
   "BballIQ": 62,
   "FG_RA_POT": 48,
   "FG_ITP_POT": 48,
   "FG_MID_POT": 40,
   "FG_COR_POT": 38,
   "FG_ATB_POT": 91,
   "FT_POT": 41,
   "Scoring_POT": 51,
   "Passing_POT": 44,
   "Handling_POT": 38,
   "OReb_POT": 40,
   "DReb_POT": 55,
   "Block_POT": 46,
   "Steal_POT": 45,
   "DrawFoul_POT": 20,
   "Defender_POT": 54,
   "Discipline_POT": 84,
   "BballIQ_POT": 69
 },
 {
   "FirstName": "Deyonta",
   "LastName": "Davis",
   "Position": 4,
   "Age": 19,
   "CollegeYear": 1,
   "Height": 83,
   "DisplayHeight": "6-11",
   "Weight": 237,
   "College": "Michigan State",
   "Consistency": 41,
   "Greed": 67,
   "Loyalty": 66,
   "PlayForWinner": 81,
   "PlayingTime": 75,
   "Personality": 73,
   "Durability": 63,
   "WorkEthic": 55,
   "DunkRate": 74,
   "RARate": 2,
   "DriveKick": 48,
   "DriveShot": 28,
   "PostUp": 67,
   "PullUp": 39,
   "CS": 23,
   "Pass": 10,
   "LocATB": 32,
   "LocCorner": 61,
   "LocMidrange": 38,
   "LocPaint": 55,
   "FG_RA": 51,
   "FG_ITP": 51,
   "FG_MID": 31,
   "FG_COR": 44,
   "FG_ATB": 79,
   "FT": 34,
   "Scoring": 56,
   "Passing": 49,
   "Handling": 46,
   "OReb": 36,
   "DReb": 51,
   "Block": 28,
   "Steal": 44,
   "DrawFoul": 8,
   "Defender": 56,
   "Discipline": 57,
   "BballIQ": 61,
   "FG_RA_POT": 58,
   "FG_ITP_POT": 58,
   "FG_MID_POT": 38,
   "FG_COR_POT": 51,
   "FG_ATB_POT": 86,
   "FT_POT": 41,
   "Scoring_POT": 63,
   "Passing_POT": 56,
   "Handling_POT": 53,
   "OReb_POT": 43,
   "DReb_POT": 58,
   "Block_POT": 35,
   "Steal_POT": 51,
   "DrawFoul_POT": 15,
   "Defender_POT": 63,
   "Discipline_POT": 64,
   "BballIQ_POT": 68
 },
 {
   "FirstName": "Marcus",
   "LastName": "Derrickson",
   "Position": 3,
   "Age": 21,
   "CollegeYear": 1,
   "Height": 79,
   "DisplayHeight": "6-7",
   "Weight": 250,
   "College": "Georgetown",
   "Consistency": 35,
   "Greed": 97,
   "Loyalty": 57,
   "PlayForWinner": 12,
   "PlayingTime": 61,
   "Personality": 20,
   "Durability": 46,
   "WorkEthic": 31,
   "DunkRate": 88,
   "RARate": 5,
   "DriveKick": 53,
   "DriveShot": 33,
   "PostUp": 26,
   "PullUp": 36,
   "CS": 40,
   "Pass": 34,
   "LocATB": 40,
   "LocCorner": 78,
   "LocMidrange": 32,
   "LocPaint": 51,
   "FG_RA": 56,
   "FG_ITP": 56,
   "FG_MID": 29,
   "FG_COR": 33,
   "FG_ATB": 72,
   "FT": 29,
   "Scoring": 52,
   "Passing": 33,
   "Handling": 44,
   "OReb": 32,
   "DReb": 42,
   "Block": 23,
   "Steal": 52,
   "DrawFoul": 5,
   "Defender": 57,
   "Discipline": 83,
   "BballIQ": 61,
   "FG_RA_POT": 63,
   "FG_ITP_POT": 63,
   "FG_MID_POT": 36,
   "FG_COR_POT": 40,
   "FG_ATB_POT": 79,
   "FT_POT": 36,
   "Scoring_POT": 59,
   "Passing_POT": 40,
   "Handling_POT": 51,
   "OReb_POT": 39,
   "DReb_POT": 49,
   "Block_POT": 30,
   "Steal_POT": 59,
   "DrawFoul_POT": 12,
   "Defender_POT": 64,
   "Discipline_POT": 90,
   "BballIQ_POT": 68
 },
 {
   "FirstName": "Dikembe",
   "LastName": "Dixson",
   "Position": 3,
   "Age": 22,
   "CollegeYear": 3,
   "Height": 78,
   "DisplayHeight": "6-6",
   "Weight": 200,
   "College": "Illinois-Chicago",
   "Consistency": 85,
   "Greed": 72,
   "Loyalty": 59,
   "PlayForWinner": 49,
   "PlayingTime": 43,
   "Personality": 50,
   "Durability": 61,
   "WorkEthic": 74,
   "DunkRate": 69,
   "RARate": 5,
   "DriveKick": 78,
   "DriveShot": 12,
   "PostUp": 33,
   "PullUp": 42,
   "CS": 34,
   "Pass": 33,
   "LocATB": 38,
   "LocCorner": 83,
   "LocMidrange": 28,
   "LocPaint": 49,
   "FG_RA": 65,
   "FG_ITP": 65,
   "FG_MID": 11,
   "FG_COR": 35,
   "FG_ATB": 77,
   "FT": 40,
   "Scoring": 43,
   "Passing": 39,
   "Handling": 55,
   "OReb": 50,
   "DReb": 41,
   "Block": 31,
   "Steal": 54,
   "DrawFoul": 2,
   "Defender": 56,
   "Discipline": 82,
   "BballIQ": 51,
   "FG_RA_POT": 72,
   "FG_ITP_POT": 72,
   "FG_MID_POT": 18,
   "FG_COR_POT": 42,
   "FG_ATB_POT": 84,
   "FT_POT": 47,
   "Scoring_POT": 50,
   "Passing_POT": 46,
   "Handling_POT": 62,
   "OReb_POT": 57,
   "DReb_POT": 48,
   "Block_POT": 38,
   "Steal_POT": 61,
   "DrawFoul_POT": 9,
   "Defender_POT": 63,
   "Discipline_POT": 89,
   "BballIQ_POT": 58
 },
 {
   "FirstName": "Trevon",
   "LastName": "Duval",
   "Position": 1,
   "Age": 20,
   "CollegeYear": 3,
   "Height": 75,
   "DisplayHeight": "6-3",
   "Weight": 190,
   "College": "Duke",
   "Consistency": 31,
   "Greed": 68,
   "Loyalty": 28,
   "PlayForWinner": 19,
   "PlayingTime": 25,
   "Personality": 20,
   "Durability": 89,
   "WorkEthic": 99,
   "DunkRate": 42,
   "RARate": 3,
   "DriveKick": 28,
   "DriveShot": 8,
   "PostUp": 0,
   "PullUp": 26,
   "CS": 50,
   "Pass": 50,
   "LocATB": 37,
   "LocCorner": 76,
   "LocMidrange": 29,
   "LocPaint": 47,
   "FG_RA": 53,
   "FG_ITP": 53,
   "FG_MID": 44,
   "FG_COR": 39,
   "FG_ATB": 68,
   "FT": 37,
   "Scoring": 47,
   "Passing": 35,
   "Handling": 36,
   "OReb": 64,
   "DReb": 51,
   "Block": 51,
   "Steal": 35,
   "DrawFoul": 4,
   "Defender": 56,
   "Discipline": 52,
   "BballIQ": 48,
   "FG_RA_POT": 60,
   "FG_ITP_POT": 60,
   "FG_MID_POT": 51,
   "FG_COR_POT": 46,
   "FG_ATB_POT": 75,
   "FT_POT": 44,
   "Scoring_POT": 54,
   "Passing_POT": 42,
   "Handling_POT": 43,
   "OReb_POT": 71,
   "DReb_POT": 58,
   "Block_POT": 58,
   "Steal_POT": 42,
   "DrawFoul_POT": 11,
   "Defender_POT": 63,
   "Discipline_POT": 59,
   "BballIQ_POT": 55
 },
 {
   "FirstName": "Drew",
   "LastName": "Eubanks",
   "Position": 4,
   "Age": 22,
   "CollegeYear": 3,
   "Height": 82,
   "DisplayHeight": "6-10",
   "Weight": 250,
   "College": "Oregon State",
   "Consistency": 67,
   "Greed": 62,
   "Loyalty": 81,
   "PlayForWinner": 46,
   "PlayingTime": 41,
   "Personality": 67,
   "Durability": 54,
   "WorkEthic": 50,
   "DunkRate": 33,
   "RARate": 10,
   "DriveKick": 77,
   "DriveShot": 0,
   "PostUp": 0,
   "PullUp": 46,
   "CS": 54,
   "Pass": 46,
   "LocATB": 35,
   "LocCorner": 80,
   "LocMidrange": 24,
   "LocPaint": 46,
   "FG_RA": 51,
   "FG_ITP": 51,
   "FG_MID": 36,
   "FG_COR": 30,
   "FG_ATB": 74,
   "FT": 20,
   "Scoring": 57,
   "Passing": 44,
   "Handling": 66,
   "OReb": 33,
   "DReb": 38,
   "Block": 30,
   "Steal": 52,
   "DrawFoul": 10,
   "Defender": 47,
   "Discipline": 74,
   "BballIQ": 53,
   "FG_RA_POT": 58,
   "FG_ITP_POT": 58,
   "FG_MID_POT": 43,
   "FG_COR_POT": 37,
   "FG_ATB_POT": 81,
   "FT_POT": 27,
   "Scoring_POT": 64,
   "Passing_POT": 51,
   "Handling_POT": 73,
   "OReb_POT": 40,
   "DReb_POT": 45,
   "Block_POT": 37,
   "Steal_POT": 59,
   "DrawFoul_POT": 17,
   "Defender_POT": 54,
   "Discipline_POT": 81,
   "BballIQ_POT": 60
 },
 {
   "FirstName": "Markelle",
   "LastName": "Fultz",
   "Position": 1,
   "Age": 19,
   "CollegeYear": 1,
   "Height": 76,
   "DisplayHeight": "6-4",
   "Weight": 200,
   "College": "Washington",
   "Consistency": 61,
   "Greed": 83,
   "Loyalty": 77,
   "PlayForWinner": 80,
   "PlayingTime": 81,
   "Personality": 76,
   "Durability": 44,
   "WorkEthic": 79,
   "DunkRate": 80,
   "RARate": 17,
   "DriveKick": 51,
   "DriveShot": 28,
   "PostUp": 20,
   "PullUp": 40,
   "CS": 45,
   "Pass": 35,
   "LocATB": 40,
   "LocCorner": 84,
   "LocMidrange": 35,
   "LocPaint": 54,
   "FG_RA": 54,
   "FG_ITP": 54,
   "FG_MID": 39,
   "FG_COR": 26,
   "FG_ATB": 66,
   "FT": 2,
   "Scoring": 40,
   "Passing": 27,
   "Handling": 36,
   "OReb": 57,
   "DReb": 65,
   "Block": 37,
   "Steal": 39,
   "DrawFoul": 13,
   "Defender": 61,
   "Discipline": 54,
   "BballIQ": 58,
   "FG_RA_POT": 61,
   "FG_ITP_POT": 61,
   "FG_MID_POT": 46,
   "FG_COR_POT": 33,
   "FG_ATB_POT": 73,
   "FT_POT": 9,
   "Scoring_POT": 47,
   "Passing_POT": 34,
   "Handling_POT": 43,
   "OReb_POT": 64,
   "DReb_POT": 72,
   "Block_POT": 44,
   "Steal_POT": 46,
   "DrawFoul_POT": 20,
   "Defender_POT": 68,
   "Discipline_POT": 61,
   "BballIQ_POT": 65
 },
 {
   "FirstName": "Kaiser",
   "LastName": "Gates",
   "Position": 3,
   "Age": 20,
   "CollegeYear": 4,
   "Height": 80,
   "DisplayHeight": "6-8",
   "Weight": 217,
   "College": "Xavier",
   "Consistency": 73,
   "Greed": 29,
   "Loyalty": 54,
   "PlayForWinner": 19,
   "PlayingTime": 26,
   "Personality": 34,
   "Durability": 54,
   "WorkEthic": 30,
   "DunkRate": 41,
   "RARate": 17,
   "DriveKick": 48,
   "DriveShot": 24,
   "PostUp": 40,
   "PullUp": 20,
   "CS": 30,
   "Pass": 30,
   "LocATB": 39,
   "LocCorner": 70,
   "LocMidrange": 42,
   "LocPaint": 52,
   "FG_RA": 55,
   "FG_ITP": 55,
   "FG_MID": 35,
   "FG_COR": 46,
   "FG_ATB": 88,
   "FT": 38,
   "Scoring": 43,
   "Passing": 43,
   "Handling": 46,
   "OReb": 48,
   "DReb": 33,
   "Block": 45,
   "Steal": 59,
   "DrawFoul": 9,
   "Defender": 46,
   "Discipline": 44,
   "BballIQ": 67,
   "FG_RA_POT": 62,
   "FG_ITP_POT": 62,
   "FG_MID_POT": 42,
   "FG_COR_POT": 53,
   "FG_ATB_POT": 95,
   "FT_POT": 45,
   "Scoring_POT": 50,
   "Passing_POT": 50,
   "Handling_POT": 53,
   "OReb_POT": 55,
   "DReb_POT": 40,
   "Block_POT": 52,
   "Steal_POT": 66,
   "DrawFoul_POT": 16,
   "Defender_POT": 53,
   "Discipline_POT": 51,
   "BballIQ_POT": 74
 },
 {
   "FirstName": "AJ",
   "LastName": "Hammons",
   "Position": 5,
   "Age": 24,
   "CollegeYear": 2,
   "Height": 84,
   "DisplayHeight": "7-0",
   "Weight": 278,
   "College": "Purdue",
   "Consistency": 55,
   "Greed": 61,
   "Loyalty": 61,
   "PlayForWinner": 58,
   "PlayingTime": 50,
   "Personality": 66,
   "Durability": 64,
   "WorkEthic": 57,
   "DunkRate": 52,
   "RARate": 14,
   "DriveKick": 34,
   "DriveShot": 7,
   "PostUp": 31,
   "PullUp": 8,
   "CS": 42,
   "Pass": 27,
   "LocATB": 26,
   "LocCorner": 73,
   "LocMidrange": 35,
   "LocPaint": 50,
   "FG_RA": 52,
   "FG_ITP": 52,
   "FG_MID": 35,
   "FG_COR": 35,
   "FG_ATB": 74,
   "FT": 23,
   "Scoring": 53,
   "Passing": 36,
   "Handling": 72,
   "OReb": 47,
   "DReb": 37,
   "Block": 25,
   "Steal": 49,
   "DrawFoul": 11,
   "Defender": 50,
   "Discipline": 52,
   "BballIQ": 55,
   "FG_RA_POT": 59,
   "FG_ITP_POT": 59,
   "FG_MID_POT": 42,
   "FG_COR_POT": 42,
   "FG_ATB_POT": 81,
   "FT_POT": 30,
   "Scoring_POT": 60,
   "Passing_POT": 43,
   "Handling_POT": 79,
   "OReb_POT": 54,
   "DReb_POT": 44,
   "Block_POT": 32,
   "Steal_POT": 56,
   "DrawFoul_POT": 18,
   "Defender_POT": 57,
   "Discipline_POT": 59,
   "BballIQ_POT": 62
 },
 {
   "FirstName": "Shaquille",
   "LastName": "Harrison",
   "Position": 1,
   "Age": 21,
   "CollegeYear": 1,
   "Height": 76,
   "DisplayHeight": "6-4",
   "Weight": 185,
   "College": "Tulsa",
   "Consistency": 47,
   "Greed": 40,
   "Loyalty": 37,
   "PlayForWinner": 77,
   "PlayingTime": 34,
   "Personality": 80,
   "Durability": 37,
   "WorkEthic": 69,
   "DunkRate": 78,
   "RARate": 3,
   "DriveKick": 68,
   "DriveShot": 26,
   "PostUp": 27,
   "PullUp": 50,
   "CS": 33,
   "Pass": 40,
   "LocATB": 41,
   "LocCorner": 86,
   "LocMidrange": 33,
   "LocPaint": 59,
   "FG_RA": 56,
   "FG_ITP": 56,
   "FG_MID": 29,
   "FG_COR": 34,
   "FG_ATB": 83,
   "FT": 28,
   "Scoring": 70,
   "Passing": 57,
   "Handling": 56,
   "OReb": 28,
   "DReb": 40,
   "Block": 29,
   "Steal": 73,
   "DrawFoul": 5,
   "Defender": 59,
   "Discipline": 64,
   "BballIQ": 58,
   "FG_RA_POT": 63,
   "FG_ITP_POT": 63,
   "FG_MID_POT": 36,
   "FG_COR_POT": 41,
   "FG_ATB_POT": 90,
   "FT_POT": 35,
   "Scoring_POT": 77,
   "Passing_POT": 64,
   "Handling_POT": 63,
   "OReb_POT": 35,
   "DReb_POT": 47,
   "Block_POT": 36,
   "Steal_POT": 80,
   "DrawFoul_POT": 12,
   "Defender_POT": 66,
   "Discipline_POT": 71,
   "BballIQ_POT": 65
 },
 {
   "FirstName": "Wesley",
   "LastName": "Iwundu",
   "Position": 2,
   "Age": 22,
   "CollegeYear": 2,
   "Height": 79,
   "DisplayHeight": "6-7",
   "Weight": 195,
   "College": "Kansas State",
   "Consistency": 82,
   "Greed": 37,
   "Loyalty": 77,
   "PlayForWinner": 86,
   "PlayingTime": 66,
   "Personality": 77,
   "Durability": 67,
   "WorkEthic": 88,
   "DunkRate": 92,
   "RARate": 3,
   "DriveKick": 74,
   "DriveShot": 11,
   "PostUp": 17,
   "PullUp": 15,
   "CS": 33,
   "Pass": 50,
   "LocATB": 38,
   "LocCorner": 74,
   "LocMidrange": 28,
   "LocPaint": 50,
   "FG_RA": 65,
   "FG_ITP": 65,
   "FG_MID": 31,
   "FG_COR": 38,
   "FG_ATB": 68,
   "FT": 29,
   "Scoring": 39,
   "Passing": 17,
   "Handling": 41,
   "OReb": 32,
   "DReb": 59,
   "Block": 49,
   "Steal": 42,
   "DrawFoul": 5,
   "Defender": 58,
   "Discipline": 58,
   "BballIQ": 57,
   "FG_RA_POT": 72,
   "FG_ITP_POT": 72,
   "FG_MID_POT": 38,
   "FG_COR_POT": 45,
   "FG_ATB_POT": 75,
   "FT_POT": 36,
   "Scoring_POT": 46,
   "Passing_POT": 24,
   "Handling_POT": 48,
   "OReb_POT": 39,
   "DReb_POT": 66,
   "Block_POT": 56,
   "Steal_POT": 49,
   "DrawFoul_POT": 12,
   "Defender_POT": 65,
   "Discipline_POT": 65,
   "BballIQ_POT": 64
 },
 {
   "FirstName": "Jaren",
   "LastName": "Jackson Jr.",
   "Position": 5,
   "Age": 18,
   "CollegeYear": 1,
   "Height": 83,
   "DisplayHeight": "6-11",
   "Weight": 242,
   "College": "Michigan State",
   "Consistency": 25,
   "Greed": 50,
   "Loyalty": 53,
   "PlayForWinner": 60,
   "PlayingTime": 64,
   "Personality": 48,
   "Durability": 40,
   "WorkEthic": 87,
   "DunkRate": 45,
   "RARate": 19,
   "DriveKick": 26,
   "DriveShot": 0,
   "PostUp": 0,
   "PullUp": 33,
   "CS": 42,
   "Pass": 58,
   "LocATB": 44,
   "LocCorner": 91,
   "LocMidrange": 25,
   "LocPaint": 48,
   "FG_RA": 51,
   "FG_ITP": 51,
   "FG_MID": 34,
   "FG_COR": 32,
   "FG_ATB": 68,
   "FT": 30,
   "Scoring": 37,
   "Passing": 38,
   "Handling": 41,
   "OReb": 43,
   "DReb": 38,
   "Block": 35,
   "Steal": 61,
   "DrawFoul": 2,
   "Defender": 44,
   "Discipline": 57,
   "BballIQ": 57,
   "FG_RA_POT": 58,
   "FG_ITP_POT": 58,
   "FG_MID_POT": 41,
   "FG_COR_POT": 39,
   "FG_ATB_POT": 75,
   "FT_POT": 37,
   "Scoring_POT": 44,
   "Passing_POT": 45,
   "Handling_POT": 48,
   "OReb_POT": 50,
   "DReb_POT": 45,
   "Block_POT": 42,
   "Steal_POT": 68,
   "DrawFoul_POT": 9,
   "Defender_POT": 51,
   "Discipline_POT": 64,
   "BballIQ_POT": 64
 },
 {
   "FirstName": "Alize",
   "LastName": "Johnson",
   "Position": 4,
   "Age": 22,
   "CollegeYear": 2,
   "Height": 81,
   "DisplayHeight": "6-9",
   "Weight": 212,
   "College": "Missouri State",
   "Consistency": 50,
   "Greed": 75,
   "Loyalty": 44,
   "PlayForWinner": 46,
   "PlayingTime": 47,
   "Personality": 53,
   "Durability": 57,
   "WorkEthic": 77,
   "DunkRate": 66,
   "RARate": 4,
   "DriveKick": 46,
   "DriveShot": 0,
   "PostUp": 0,
   "PullUp": 24,
   "CS": 44,
   "Pass": 56,
   "LocATB": 41,
   "LocCorner": 71,
   "LocMidrange": 34,
   "LocPaint": 47,
   "FG_RA": 63,
   "FG_ITP": 63,
   "FG_MID": 37,
   "FG_COR": 37,
   "FG_ATB": 69,
   "FT": 33,
   "Scoring": 52,
   "Passing": 26,
   "Handling": 53,
   "OReb": 74,
   "DReb": 19,
   "Block": 44,
   "Steal": 45,
   "DrawFoul": 7,
   "Defender": 58,
   "Discipline": 72,
   "BballIQ": 66,
   "FG_RA_POT": 70,
   "FG_ITP_POT": 70,
   "FG_MID_POT": 44,
   "FG_COR_POT": 44,
   "FG_ATB_POT": 76,
   "FT_POT": 40,
   "Scoring_POT": 59,
   "Passing_POT": 33,
   "Handling_POT": 60,
   "OReb_POT": 81,
   "DReb_POT": 26,
   "Block_POT": 51,
   "Steal_POT": 52,
   "DrawFoul_POT": 14,
   "Defender_POT": 65,
   "Discipline_POT": 79,
   "BballIQ_POT": 73
 },
 {
   "FirstName": "Maxi",
   "LastName": "Kleber",
   "Position": 5,
   "Age": 25,
   "CollegeYear": 1,
   "Height": 83,
   "DisplayHeight": "6-11",
   "Weight": 240,
   "College": "Germany",
   "Consistency": 92,
   "Greed": 14,
   "Loyalty": 87,
   "PlayForWinner": 66,
   "PlayingTime": 81,
   "Personality": 75,
   "Durability": 84,
   "WorkEthic": 83,
   "DunkRate": 88,
   "RARate": 10,
   "DriveKick": 81,
   "DriveShot": 7,
   "PostUp": 17,
   "PullUp": 21,
   "CS": 33,
   "Pass": 50,
   "LocATB": 39,
   "LocCorner": 70,
   "LocMidrange": 30,
   "LocPaint": 51,
   "FG_RA": 59,
   "FG_ITP": 59,
   "FG_MID": 39,
   "FG_COR": 42,
   "FG_ATB": 70,
   "FT": 0,
   "Scoring": 37,
   "Passing": 26,
   "Handling": 33,
   "OReb": 69,
   "DReb": 50,
   "Block": 42,
   "Steal": 46,
   "DrawFoul": 6,
   "Defender": 54,
   "Discipline": 64,
   "BballIQ": 46,
   "FG_RA_POT": 66,
   "FG_ITP_POT": 66,
   "FG_MID_POT": 46,
   "FG_COR_POT": 49,
   "FG_ATB_POT": 77,
   "FT_POT": 7,
   "Scoring_POT": 44,
   "Passing_POT": 33,
   "Handling_POT": 40,
   "OReb_POT": 76,
   "DReb_POT": 57,
   "Block_POT": 49,
   "Steal_POT": 53,
   "DrawFoul_POT": 13,
   "Defender_POT": 61,
   "Discipline_POT": 71,
   "BballIQ_POT": 53
 },
 {
   "FirstName": "TJ",
   "LastName": "Leaf",
   "Position": 4,
   "Age": 20,
   "CollegeYear": 4,
   "Height": 82,
   "DisplayHeight": "6-10",
   "Weight": 225,
   "College": "UCLA",
   "Consistency": 66,
   "Greed": 49,
   "Loyalty": 35,
   "PlayForWinner": 53,
   "PlayingTime": 29,
   "Personality": 80,
   "Durability": 34,
   "WorkEthic": 22,
   "DunkRate": 63,
   "RARate": 11,
   "DriveKick": 46,
   "DriveShot": 33,
   "PostUp": 50,
   "PullUp": 50,
   "CS": 35,
   "Pass": 15,
   "LocATB": 19,
   "LocCorner": 54,
   "LocMidrange": 38,
   "LocPaint": 69,
   "FG_RA": 51,
   "FG_ITP": 51,
   "FG_MID": 32,
   "FG_COR": 33,
   "FG_ATB": 73,
   "FT": 33,
   "Scoring": 51,
   "Passing": 31,
   "Handling": 55,
   "OReb": 37,
   "DReb": 45,
   "Block": 18,
   "Steal": 62,
   "DrawFoul": 6,
   "Defender": 47,
   "Discipline": 64,
   "BballIQ": 67,
   "FG_RA_POT": 58,
   "FG_ITP_POT": 58,
   "FG_MID_POT": 39,
   "FG_COR_POT": 40,
   "FG_ATB_POT": 80,
   "FT_POT": 40,
   "Scoring_POT": 58,
   "Passing_POT": 38,
   "Handling_POT": 62,
   "OReb_POT": 44,
   "DReb_POT": 52,
   "Block_POT": 25,
   "Steal_POT": 69,
   "DrawFoul_POT": 13,
   "Defender_POT": 54,
   "Discipline_POT": 71,
   "BballIQ_POT": 74
 },
 {
   "FirstName": "Walt",
   "LastName": "Lemon",
   "Position": 1,
   "Age": 25,
   "CollegeYear": 3,
   "Height": 75,
   "DisplayHeight": "6-3",
   "Weight": 180,
   "College": "Bradley",
   "Consistency": 66,
   "Greed": 96,
   "Loyalty": 55,
   "PlayForWinner": 73,
   "PlayingTime": 81,
   "Personality": 45,
   "Durability": 56,
   "WorkEthic": 72,
   "DunkRate": 70,
   "RARate": 14,
   "DriveKick": 32,
   "DriveShot": 16,
   "PostUp": 10,
   "PullUp": 3,
   "CS": 13,
   "Pass": 77,
   "LocATB": 37,
   "LocCorner": 67,
   "LocMidrange": 35,
   "LocPaint": 50,
   "FG_RA": 58,
   "FG_ITP": 58,
   "FG_MID": 39,
   "FG_COR": 34,
   "FG_ATB": 76,
   "FT": 37,
   "Scoring": 45,
   "Passing": 35,
   "Handling": 51,
   "OReb": 23,
   "DReb": 42,
   "Block": 21,
   "Steal": 43,
   "DrawFoul": 10,
   "Defender": 50,
   "Discipline": 78,
   "BballIQ": 50,
   "FG_RA_POT": 65,
   "FG_ITP_POT": 65,
   "FG_MID_POT": 46,
   "FG_COR_POT": 41,
   "FG_ATB_POT": 83,
   "FT_POT": 44,
   "Scoring_POT": 52,
   "Passing_POT": 42,
   "Handling_POT": 58,
   "OReb_POT": 30,
   "DReb_POT": 49,
   "Block_POT": 28,
   "Steal_POT": 50,
   "DrawFoul_POT": 17,
   "Defender_POT": 57,
   "Discipline_POT": 85,
   "BballIQ_POT": 57
 },
 {
   "FirstName": "Tyler",
   "LastName": "Lydon",
   "Position": 4,
   "Age": 21,
   "CollegeYear": 1,
   "Height": 82,
   "DisplayHeight": "6-10",
   "Weight": 225,
   "College": "Syracuse",
   "Consistency": 55,
   "Greed": 99,
   "Loyalty": 16,
   "PlayForWinner": 75,
   "PlayingTime": 88,
   "Personality": 35,
   "Durability": 95,
   "WorkEthic": 88,
   "DunkRate": 90,
   "RARate": 23,
   "DriveKick": 72,
   "DriveShot": 34,
   "PostUp": 33,
   "PullUp": 35,
   "CS": 34,
   "Pass": 33,
   "LocATB": 37,
   "LocCorner": 75,
   "LocMidrange": 37,
   "LocPaint": 58,
   "FG_RA": 60,
   "FG_ITP": 60,
   "FG_MID": 29,
   "FG_COR": 35,
   "FG_ATB": 73,
   "FT": 27,
   "Scoring": 46,
   "Passing": 36,
   "Handling": 45,
   "OReb": 33,
   "DReb": 53,
   "Block": 31,
   "Steal": 34,
   "DrawFoul": 5,
   "Defender": 54,
   "Discipline": 61,
   "BballIQ": 54,
   "FG_RA_POT": 67,
   "FG_ITP_POT": 67,
   "FG_MID_POT": 36,
   "FG_COR_POT": 42,
   "FG_ATB_POT": 80,
   "FT_POT": 34,
   "Scoring_POT": 53,
   "Passing_POT": 43,
   "Handling_POT": 52,
   "OReb_POT": 40,
   "DReb_POT": 60,
   "Block_POT": 38,
   "Steal_POT": 41,
   "DrawFoul_POT": 12,
   "Defender_POT": 61,
   "Discipline_POT": 68,
   "BballIQ_POT": 61
 },
 {
   "FirstName": "JP",
   "LastName": "Macura",
   "Position": 2,
   "Age": 23,
   "CollegeYear": 2,
   "Height": 77,
   "DisplayHeight": "6-5",
   "Weight": 203,
   "College": "Xavier",
   "Consistency": 15,
   "Greed": 35,
   "Loyalty": 26,
   "PlayForWinner": 14,
   "PlayingTime": 19,
   "Personality": 27,
   "Durability": 32,
   "WorkEthic": 69,
   "DunkRate": 69,
   "RARate": 7,
   "DriveKick": 51,
   "DriveShot": 31,
   "PostUp": 56,
   "PullUp": 34,
   "CS": 44,
   "Pass": 0,
   "LocATB": 34,
   "LocCorner": 70,
   "LocMidrange": 41,
   "LocPaint": 52,
   "FG_RA": 49,
   "FG_ITP": 49,
   "FG_MID": 35,
   "FG_COR": 40,
   "FG_ATB": 74,
   "FT": 34,
   "Scoring": 42,
   "Passing": 30,
   "Handling": 42,
   "OReb": 43,
   "DReb": 44,
   "Block": 46,
   "Steal": 37,
   "DrawFoul": 0,
   "Defender": 51,
   "Discipline": 58,
   "BballIQ": 62,
   "FG_RA_POT": 56,
   "FG_ITP_POT": 56,
   "FG_MID_POT": 42,
   "FG_COR_POT": 47,
   "FG_ATB_POT": 81,
   "FT_POT": 41,
   "Scoring_POT": 49,
   "Passing_POT": 37,
   "Handling_POT": 49,
   "OReb_POT": 50,
   "DReb_POT": 51,
   "Block_POT": 53,
   "Steal_POT": 44,
   "DrawFoul_POT": 7,
   "Defender_POT": 58,
   "Discipline_POT": 65,
   "BballIQ_POT": 69
 },
 {
   "FirstName": "Brandon",
   "LastName": "McCoy",
   "Position": 5,
   "Age": 20,
   "CollegeYear": 3,
   "Height": 85,
   "DisplayHeight": "7-1",
   "Weight": 250,
   "College": "UNLV",
   "Consistency": 77,
   "Greed": 80,
   "Loyalty": 77,
   "PlayForWinner": 74,
   "PlayingTime": 70,
   "Personality": 81,
   "Durability": 84,
   "WorkEthic": 72,
   "DunkRate": 76,
   "RARate": 26,
   "DriveKick": 39,
   "DriveShot": 56,
   "PostUp": 91,
   "PullUp": 50,
   "CS": 9,
   "Pass": 0,
   "LocATB": 34,
   "LocCorner": 58,
   "LocMidrange": 27,
   "LocPaint": 62,
   "FG_RA": 53,
   "FG_ITP": 53,
   "FG_MID": 31,
   "FG_COR": 34,
   "FG_ATB": 80,
   "FT": 33,
   "Scoring": 36,
   "Passing": 51,
   "Handling": 63,
   "OReb": 41,
   "DReb": 33,
   "Block": 23,
   "Steal": 63,
   "DrawFoul": 2,
   "Defender": 44,
   "Discipline": 68,
   "BballIQ": 61,
   "FG_RA_POT": 60,
   "FG_ITP_POT": 60,
   "FG_MID_POT": 38,
   "FG_COR_POT": 41,
   "FG_ATB_POT": 87,
   "FT_POT": 40,
   "Scoring_POT": 43,
   "Passing_POT": 58,
   "Handling_POT": 70,
   "OReb_POT": 48,
   "DReb_POT": 40,
   "Block_POT": 30,
   "Steal_POT": 70,
   "DrawFoul_POT": 9,
   "Defender_POT": 51,
   "Discipline_POT": 75,
   "BballIQ_POT": 68
 },
 {
   "FirstName": "Alfonzo",
   "LastName": "McKinnie",
   "Position": 3,
   "Age": 25,
   "CollegeYear": 4,
   "Height": 80,
   "DisplayHeight": "6-8",
   "Weight": 215,
   "College": "Green Bay",
   "Consistency": 47,
   "Greed": 64,
   "Loyalty": 66,
   "PlayForWinner": 37,
   "PlayingTime": 28,
   "Personality": 55,
   "Durability": 55,
   "WorkEthic": 15,
   "DunkRate": 46,
   "RARate": 10,
   "DriveKick": 71,
   "DriveShot": 38,
   "PostUp": 66,
   "PullUp": 10,
   "CS": 34,
   "Pass": 0,
   "LocATB": 35,
   "LocCorner": 60,
   "LocMidrange": 41,
   "LocPaint": 62,
   "FG_RA": 55,
   "FG_ITP": 55,
   "FG_MID": 35,
   "FG_COR": 46,
   "FG_ATB": 88,
   "FT": 38,
   "Scoring": 43,
   "Passing": 43,
   "Handling": 46,
   "OReb": 48,
   "DReb": 33,
   "Block": 45,
   "Steal": 59,
   "DrawFoul": 9,
   "Defender": 46,
   "Discipline": 44,
   "BballIQ": 67,
   "FG_RA_POT": 62,
   "FG_ITP_POT": 62,
   "FG_MID_POT": 42,
   "FG_COR_POT": 53,
   "FG_ATB_POT": 95,
   "FT_POT": 45,
   "Scoring_POT": 50,
   "Passing_POT": 50,
   "Handling_POT": 53,
   "OReb_POT": 55,
   "DReb_POT": 40,
   "Block_POT": 52,
   "Steal_POT": 66,
   "DrawFoul_POT": 16,
   "Defender_POT": 53,
   "Discipline_POT": 51,
   "BballIQ_POT": 74
 },
 {
   "FirstName": "De'Anthony",
   "LastName": "Melton",
   "Position": 1,
   "Age": 19,
   "CollegeYear": 4,
   "Height": 75,
   "DisplayHeight": "6-3",
   "Weight": 193,
   "College": "USC",
   "Consistency": 77,
   "Greed": 80,
   "Loyalty": 72,
   "PlayForWinner": 40,
   "PlayingTime": 60,
   "Personality": 67,
   "Durability": 65,
   "WorkEthic": 60,
   "DunkRate": 75,
   "RARate": 30,
   "DriveKick": 81,
   "DriveShot": 36,
   "PostUp": 87,
   "PullUp": 42,
   "CS": 13,
   "Pass": 0,
   "LocATB": 27,
   "LocCorner": 47,
   "LocMidrange": 33,
   "LocPaint": 59,
   "FG_RA": 53,
   "FG_ITP": 53,
   "FG_MID": 31,
   "FG_COR": 34,
   "FG_ATB": 80,
   "FT": 33,
   "Scoring": 36,
   "Passing": 51,
   "Handling": 63,
   "OReb": 41,
   "DReb": 33,
   "Block": 23,
   "Steal": 63,
   "DrawFoul": 2,
   "Defender": 44,
   "Discipline": 68,
   "BballIQ": 61,
   "FG_RA_POT": 60,
   "FG_ITP_POT": 60,
   "FG_MID_POT": 38,
   "FG_COR_POT": 41,
   "FG_ATB_POT": 87,
   "FT_POT": 40,
   "Scoring_POT": 43,
   "Passing_POT": 58,
   "Handling_POT": 70,
   "OReb_POT": 48,
   "DReb_POT": 40,
   "Block_POT": 30,
   "Steal_POT": 70,
   "DrawFoul_POT": 9,
   "Defender_POT": 51,
   "Discipline_POT": 75,
   "BballIQ_POT": 68
 },
 {
   "FirstName": "Chimezie",
   "LastName": "Metu",
   "Position": 4,
   "Age": 21,
   "CollegeYear": 4,
   "Height": 82,
   "DisplayHeight": "6-10",
   "Weight": 225,
   "College": "USC",
   "Consistency": 44,
   "Greed": 44,
   "Loyalty": 44,
   "PlayForWinner": 44,
   "PlayingTime": 44,
   "Personality": 44,
   "Durability": 44,
   "WorkEthic": 44,
   "DunkRate": 44,
   "RARate": 30,
   "DriveKick": 61,
   "DriveShot": 27,
   "PostUp": 27,
   "PullUp": 27,
   "CS": 73,
   "Pass": 0,
   "LocATB": 42,
   "LocCorner": 69,
   "LocMidrange": 25,
   "LocPaint": 51,
   "FG_RA": 51,
   "FG_ITP": 51,
   "FG_MID": 36,
   "FG_COR": 30,
   "FG_ATB": 74,
   "FT": 20,
   "Scoring": 57,
   "Passing": 44,
   "Handling": 66,
   "OReb": 33,
   "DReb": 38,
   "Block": 30,
   "Steal": 52,
   "DrawFoul": 10,
   "Defender": 47,
   "Discipline": 74,
   "BballIQ": 53,
   "FG_RA_POT": 58,
   "FG_ITP_POT": 58,
   "FG_MID_POT": 43,
   "FG_COR_POT": 37,
   "FG_ATB_POT": 81,
   "FT_POT": 27,
   "Scoring_POT": 64,
   "Passing_POT": 51,
   "Handling_POT": 73,
   "OReb_POT": 40,
   "DReb_POT": 45,
   "Block_POT": 37,
   "Steal_POT": 59,
   "DrawFoul_POT": 17,
   "Defender_POT": 54,
   "Discipline_POT": 81,
   "BballIQ_POT": 60
 },
 {
   "FirstName": "Naz",
   "LastName": "Mitrou-Long",
   "Position": 1,
   "Age": 24,
   "CollegeYear": 2,
   "Height": 76,
   "DisplayHeight": "6-4",
   "Weight": 215,
   "College": "Iowa State",
   "Consistency": 25,
   "Greed": 77,
   "Loyalty": 39,
   "PlayForWinner": 64,
   "PlayingTime": 70,
   "Personality": 77,
   "Durability": 35,
   "WorkEthic": 55,
   "DunkRate": 61,
   "RARate": 9,
   "DriveKick": 51,
   "DriveShot": 31,
   "PostUp": 37,
   "PullUp": 50,
   "CS": 53,
   "Pass": 10,
   "LocATB": 38,
   "LocCorner": 49,
   "LocMidrange": 33,
   "LocPaint": 56,
   "FG_RA": 63,
   "FG_ITP": 63,
   "FG_MID": 37,
   "FG_COR": 36,
   "FG_ATB": 70,
   "FT": 0,
   "Scoring": 38,
   "Passing": 33,
   "Handling": 44,
   "OReb": 46,
   "DReb": 42,
   "Block": 26,
   "Steal": 38,
   "DrawFoul": 4,
   "Defender": 54,
   "Discipline": 60,
   "BballIQ": 59,
   "FG_RA_POT": 70,
   "FG_ITP_POT": 70,
   "FG_MID_POT": 44,
   "FG_COR_POT": 43,
   "FG_ATB_POT": 77,
   "FT_POT": 7,
   "Scoring_POT": 45,
   "Passing_POT": 40,
   "Handling_POT": 51,
   "OReb_POT": 53,
   "DReb_POT": 49,
   "Block_POT": 33,
   "Steal_POT": 45,
   "DrawFoul_POT": 11,
   "Defender_POT": 61,
   "Discipline_POT": 67,
   "BballIQ_POT": 66
 },
 {
   "FirstName": "Ben",
   "LastName": "Moore",
   "Position": 3,
   "Age": 22,
   "CollegeYear": 4,
   "Height": 80,
   "DisplayHeight": "6-8",
   "Weight": 220,
   "College": "SMU",
   "Consistency": 44,
   "Greed": 41,
   "Loyalty": 46,
   "PlayForWinner": 49,
   "PlayingTime": 40,
   "Personality": 48,
   "Durability": 49,
   "WorkEthic": 48,
   "DunkRate": 47,
   "RARate": 8,
   "DriveKick": 60,
   "DriveShot": 1,
   "PostUp": 10,
   "PullUp": 10,
   "CS": 20,
   "Pass": 70,
   "LocATB": 41,
   "LocCorner": 88,
   "LocMidrange": 22,
   "LocPaint": 40,
   "FG_RA": 60,
   "FG_ITP": 60,
   "FG_MID": 39,
   "FG_COR": 29,
   "FG_ATB": 78,
   "FT": 28,
   "Scoring": 46,
   "Passing": 37,
   "Handling": 62,
   "OReb": 55,
   "DReb": 32,
   "Block": 31,
   "Steal": 61,
   "DrawFoul": 5,
   "Defender": 52,
   "Discipline": 60,
   "BballIQ": 61,
   "FG_RA_POT": 67,
   "FG_ITP_POT": 67,
   "FG_MID_POT": 46,
   "FG_COR_POT": 36,
   "FG_ATB_POT": 85,
   "FT_POT": 35,
   "Scoring_POT": 53,
   "Passing_POT": 44,
   "Handling_POT": 69,
   "OReb_POT": 62,
   "DReb_POT": 39,
   "Block_POT": 38,
   "Steal_POT": 68,
   "DrawFoul_POT": 12,
   "Defender_POT": 59,
   "Discipline_POT": 67,
   "BballIQ_POT": 68
 },
 {
   "FirstName": "Doral",
   "LastName": "Moore",
   "Position": 5,
   "Age": 21,
   "CollegeYear": 3,
   "Height": 85,
   "DisplayHeight": "7-1",
   "Weight": 265,
   "College": "Wake Forest",
   "Consistency": 74,
   "Greed": 24,
   "Loyalty": 56,
   "PlayForWinner": 60,
   "PlayingTime": 44,
   "Personality": 63,
   "Durability": 70,
   "WorkEthic": 65,
   "DunkRate": 61,
   "RARate": 21,
   "DriveKick": 52,
   "DriveShot": 17,
   "PostUp": 68,
   "PullUp": 40,
   "CS": 32,
   "Pass": 0,
   "LocATB": 38,
   "LocCorner": 41,
   "LocMidrange": 43,
   "LocPaint": 54,
   "FG_RA": 55,
   "FG_ITP": 55,
   "FG_MID": 32,
   "FG_COR": 35,
   "FG_ATB": 80,
   "FT": 32,
   "Scoring": 36,
   "Passing": 37,
   "Handling": 49,
   "OReb": 56,
   "DReb": 53,
   "Block": 41,
   "Steal": 51,
   "DrawFoul": 2,
   "Defender": 54,
   "Discipline": 79,
   "BballIQ": 52,
   "FG_RA_POT": 62,
   "FG_ITP_POT": 62,
   "FG_MID_POT": 39,
   "FG_COR_POT": 42,
   "FG_ATB_POT": 87,
   "FT_POT": 39,
   "Scoring_POT": 43,
   "Passing_POT": 44,
   "Handling_POT": 56,
   "OReb_POT": 63,
   "DReb_POT": 60,
   "Block_POT": 48,
   "Steal_POT": 58,
   "DrawFoul_POT": 9,
   "Defender_POT": 61,
   "Discipline_POT": 86,
   "BballIQ_POT": 59
 },
 {
   "FirstName": "Dzanan",
   "LastName": "Musa",
   "Position": 3,
   "Age": 19,
   "CollegeYear": 3,
   "Height": 81,
   "DisplayHeight": "6-9",
   "Weight": 195,
   "College": "Bosnia",
   "Consistency": 68,
   "Greed": 47,
   "Loyalty": 56,
   "PlayForWinner": 56,
   "PlayingTime": 61,
   "Personality": 52,
   "Durability": 71,
   "WorkEthic": 68,
   "DunkRate": 51,
   "RARate": 16,
   "DriveKick": 37,
   "DriveShot": 7,
   "PostUp": 20,
   "PullUp": 50,
   "CS": 70,
   "Pass": 10,
   "LocATB": 40,
   "LocCorner": 66,
   "LocMidrange": 32,
   "LocPaint": 52,
   "FG_RA": 56,
   "FG_ITP": 56,
   "FG_MID": 33,
   "FG_COR": 32,
   "FG_ATB": 71,
   "FT": 29,
   "Scoring": 38,
   "Passing": 35,
   "Handling": 32,
   "OReb": 43,
   "DReb": 47,
   "Block": 62,
   "Steal": 65,
   "DrawFoul": 16,
   "Defender": 48,
   "Discipline": 81,
   "BballIQ": 67,
   "FG_RA_POT": 63,
   "FG_ITP_POT": 63,
   "FG_MID_POT": 40,
   "FG_COR_POT": 39,
   "FG_ATB_POT": 78,
   "FT_POT": 36,
   "Scoring_POT": 45,
   "Passing_POT": 42,
   "Handling_POT": 39,
   "OReb_POT": 50,
   "DReb_POT": 54,
   "Block_POT": 69,
   "Steal_POT": 72,
   "DrawFoul_POT": 23,
   "Defender_POT": 55,
   "Discipline_POT": 88,
   "BballIQ_POT": 74
 },
 {
   "FirstName": "Elie",
   "LastName": "Okobo",
   "Position": 1,
   "Age": 21,
   "CollegeYear": 3,
   "Height": 74,
   "DisplayHeight": "6-2",
   "Weight": 180,
   "College": "France",
   "Consistency": 17,
   "Greed": 26,
   "Loyalty": 31,
   "PlayForWinner": 18,
   "PlayingTime": 24,
   "Personality": 50,
   "Durability": 52,
   "WorkEthic": 40,
   "DunkRate": 28,
   "RARate": 9,
   "DriveKick": 81,
   "DriveShot": 38,
   "PostUp": 39,
   "PullUp": 36,
   "CS": 61,
   "Pass": 0,
   "LocATB": 44,
   "LocCorner": 75,
   "LocMidrange": 41,
   "LocPaint": 60,
   "FG_RA": 49,
   "FG_ITP": 49,
   "FG_MID": 35,
   "FG_COR": 38,
   "FG_ATB": 79,
   "FT": 40,
   "Scoring": 57,
   "Passing": 64,
   "Handling": 56,
   "OReb": 51,
   "DReb": 47,
   "Block": 38,
   "Steal": 46,
   "DrawFoul": 7,
   "Defender": 45,
   "Discipline": 59,
   "BballIQ": 59,
   "FG_RA_POT": 56,
   "FG_ITP_POT": 56,
   "FG_MID_POT": 42,
   "FG_COR_POT": 45,
   "FG_ATB_POT": 86,
   "FT_POT": 47,
   "Scoring_POT": 64,
   "Passing_POT": 71,
   "Handling_POT": 63,
   "OReb_POT": 58,
   "DReb_POT": 54,
   "Block_POT": 45,
   "Steal_POT": 53,
   "DrawFoul_POT": 14,
   "Defender_POT": 52,
   "Discipline_POT": 66,
   "BballIQ_POT": 66
 },
 {
   "FirstName": "Josh",
   "LastName": "Okogie",
   "Position": 2,
   "Age": 20,
   "CollegeYear": 3,
   "Height": 76,
   "DisplayHeight": "6-4",
   "Weight": 212,
   "College": "Georgia Tech",
   "Consistency": 74,
   "Greed": 18,
   "Loyalty": 27,
   "PlayForWinner": 36,
   "PlayingTime": 35,
   "Personality": 54,
   "Durability": 55,
   "WorkEthic": 55,
   "DunkRate": 27,
   "RARate": 9,
   "DriveKick": 64,
   "DriveShot": 14,
   "PostUp": 10,
   "PullUp": 50,
   "CS": 34,
   "Pass": 56,
   "LocATB": 40,
   "LocCorner": 75,
   "LocMidrange": 41,
   "LocPaint": 54,
   "FG_RA": 49,
   "FG_ITP": 49,
   "FG_MID": 35,
   "FG_COR": 38,
   "FG_ATB": 79,
   "FT": 40,
   "Scoring": 57,
   "Passing": 64,
   "Handling": 56,
   "OReb": 51,
   "DReb": 47,
   "Block": 38,
   "Steal": 46,
   "DrawFoul": 7,
   "Defender": 45,
   "Discipline": 59,
   "BballIQ": 59,
   "FG_RA_POT": 56,
   "FG_ITP_POT": 56,
   "FG_MID_POT": 42,
   "FG_COR_POT": 45,
   "FG_ATB_POT": 86,
   "FT_POT": 47,
   "Scoring_POT": 64,
   "Passing_POT": 71,
   "Handling_POT": 63,
   "OReb_POT": 58,
   "DReb_POT": 54,
   "Block_POT": 45,
   "Steal_POT": 53,
   "DrawFoul_POT": 14,
   "Defender_POT": 52,
   "Discipline_POT": 66,
   "BballIQ_POT": 66
 },
 {
   "FirstName": "Cameron",
   "LastName": "Oliver",
   "Position": 4,
   "Age": 22,
   "CollegeYear": 4,
   "Height": 80,
   "DisplayHeight": "6-8",
   "Weight": 225,
   "College": "Nevada",
   "Consistency": 64,
   "Greed": 64,
   "Loyalty": 34,
   "PlayForWinner": 45,
   "PlayingTime": 23,
   "Personality": 24,
   "Durability": 65,
   "WorkEthic": 81,
   "DunkRate": 32,
   "RARate": 19,
   "DriveKick": 55,
   "DriveShot": 56,
   "PostUp": 88,
   "PullUp": 5,
   "CS": 12,
   "Pass": 0,
   "LocATB": 0,
   "LocCorner": 57,
   "LocMidrange": 22,
   "LocPaint": 68,
   "FG_RA": 62,
   "FG_ITP": 62,
   "FG_MID": 28,
   "FG_COR": 35,
   "FG_ATB": 69,
   "FT": 37,
   "Scoring": 27,
   "Passing": 42,
   "Handling": 32,
   "OReb": 53,
   "DReb": 62,
   "Block": 42,
   "Steal": 58,
   "DrawFoul": 2,
   "Defender": 45,
   "Discipline": 50,
   "BballIQ": 48,
   "FG_RA_POT": 69,
   "FG_ITP_POT": 69,
   "FG_MID_POT": 35,
   "FG_COR_POT": 42,
   "FG_ATB_POT": 76,
   "FT_POT": 44,
   "Scoring_POT": 34,
   "Passing_POT": 49,
   "Handling_POT": 39,
   "OReb_POT": 60,
   "DReb_POT": 69,
   "Block_POT": 49,
   "Steal_POT": 65,
   "DrawFoul_POT": 9,
   "Defender_POT": 52,
   "Discipline_POT": 57,
   "BballIQ_POT": 55
 },
 {
   "FirstName": "London",
   "LastName": "Perrantes",
   "Position": 1,
   "Age": 23,
   "CollegeYear": 3,
   "Height": 74,
   "DisplayHeight": "6-2",
   "Weight": 190,
   "College": "Virginia",
   "Consistency": 18,
   "Greed": 36,
   "Loyalty": 55,
   "PlayForWinner": 34,
   "PlayingTime": 19,
   "Personality": 25,
   "Durability": 59,
   "WorkEthic": 27,
   "DunkRate": 40,
   "RARate": 28,
   "DriveKick": 38,
   "DriveShot": 46,
   "PostUp": 73,
   "PullUp": 25,
   "CS": 27,
   "Pass": 0,
   "LocATB": 5,
   "LocCorner": 29,
   "LocMidrange": 41,
   "LocPaint": 67,
   "FG_RA": 66,
   "FG_ITP": 66,
   "FG_MID": 34,
   "FG_COR": 32,
   "FG_ATB": 80,
   "FT": 0,
   "Scoring": 61,
   "Passing": 24,
   "Handling": 33,
   "OReb": 57,
   "DReb": 56,
   "Block": 43,
   "Steal": 47,
   "DrawFoul": 11,
   "Defender": 46,
   "Discipline": 71,
   "BballIQ": 58,
   "FG_RA_POT": 73,
   "FG_ITP_POT": 73,
   "FG_MID_POT": 41,
   "FG_COR_POT": 39,
   "FG_ATB_POT": 87,
   "FT_POT": 7,
   "Scoring_POT": 68,
   "Passing_POT": 31,
   "Handling_POT": 40,
   "OReb_POT": 64,
   "DReb_POT": 63,
   "Block_POT": 50,
   "Steal_POT": 54,
   "DrawFoul_POT": 18,
   "Defender_POT": 53,
   "Discipline_POT": 78,
   "BballIQ_POT": 65
 },
 {
   "FirstName": "Theo",
   "LastName": "Pinson",
   "Position": 3,
   "Age": 23,
   "CollegeYear": 1,
   "Height": 78,
   "DisplayHeight": "6-6",
   "Weight": 210,
   "College": "UNC",
   "Consistency": 43,
   "Greed": 15,
   "Loyalty": 80,
   "PlayForWinner": 77,
   "PlayingTime": 37,
   "Personality": 68,
   "Durability": 79,
   "WorkEthic": 93,
   "DunkRate": 73,
   "RARate": 25,
   "DriveKick": 49,
   "DriveShot": 47,
   "PostUp": 66,
   "PullUp": 21,
   "CS": 34,
   "Pass": 0,
   "LocATB": 21,
   "LocCorner": 56,
   "LocMidrange": 32,
   "LocPaint": 58,
   "FG_RA": 62,
   "FG_ITP": 62,
   "FG_MID": 34,
   "FG_COR": 35,
   "FG_ATB": 70,
   "FT": 0,
   "Scoring": 58,
   "Passing": 46,
   "Handling": 45,
   "OReb": 44,
   "DReb": 39,
   "Block": 59,
   "Steal": 35,
   "DrawFoul": 3,
   "Defender": 47,
   "Discipline": 19,
   "BballIQ": 61,
   "FG_RA_POT": 69,
   "FG_ITP_POT": 69,
   "FG_MID_POT": 41,
   "FG_COR_POT": 42,
   "FG_ATB_POT": 77,
   "FT_POT": 7,
   "Scoring_POT": 65,
   "Passing_POT": 53,
   "Handling_POT": 52,
   "OReb_POT": 51,
   "DReb_POT": 46,
   "Block_POT": 66,
   "Steal_POT": 42,
   "DrawFoul_POT": 10,
   "Defender_POT": 54,
   "Discipline_POT": 26,
   "BballIQ_POT": 68
 },
 {
   "FirstName": "Michael",
   "LastName": "Porter",
   "Position": 4,
   "Age": 20,
   "CollegeYear": 2,
   "Height": 83,
   "DisplayHeight": "6-11",
   "Weight": 210,
   "College": "Missouri",
   "Consistency": 46,
   "Greed": 72,
   "Loyalty": 58,
   "PlayForWinner": 16,
   "PlayingTime": 26,
   "Personality": 53,
   "Durability": 47,
   "WorkEthic": 75,
   "DunkRate": 56,
   "RARate": 3,
   "DriveKick": 58,
   "DriveShot": 0,
   "PostUp": 0,
   "PullUp": 17,
   "CS": 32,
   "Pass": 68,
   "LocATB": 30,
   "LocCorner": 81,
   "LocMidrange": 27,
   "LocPaint": 42,
   "FG_RA": 58,
   "FG_ITP": 58,
   "FG_MID": 31,
   "FG_COR": 18,
   "FG_ATB": 67,
   "FT": 0,
   "Scoring": 35,
   "Passing": 40,
   "Handling": 41,
   "OReb": 51,
   "DReb": 61,
   "Block": 52,
   "Steal": 23,
   "DrawFoul": 5,
   "Defender": 54,
   "Discipline": 75,
   "BballIQ": 65,
   "FG_RA_POT": 65,
   "FG_ITP_POT": 65,
   "FG_MID_POT": 38,
   "FG_COR_POT": 25,
   "FG_ATB_POT": 74,
   "FT_POT": 7,
   "Scoring_POT": 42,
   "Passing_POT": 47,
   "Handling_POT": 48,
   "OReb_POT": 58,
   "DReb_POT": 68,
   "Block_POT": 59,
   "Steal_POT": 30,
   "DrawFoul_POT": 12,
   "Defender_POT": 61,
   "Discipline_POT": 82,
   "BballIQ_POT": 72
 },
 {
   "FirstName": "Rodney",
   "LastName": "Purvis",
   "Position": 3,
   "Age": 22,
   "CollegeYear": 4,
   "Height": 76,
   "DisplayHeight": "6-4",
   "Weight": 205,
   "College": "UCONN",
   "Consistency": 32,
   "Greed": 77,
   "Loyalty": 34,
   "PlayForWinner": 75,
   "PlayingTime": 80,
   "Personality": 69,
   "Durability": 20,
   "WorkEthic": 35,
   "DunkRate": 24,
   "RARate": 10,
   "DriveKick": 46,
   "DriveShot": 23,
   "PostUp": 45,
   "PullUp": 23,
   "CS": 18,
   "Pass": 37,
   "LocATB": 33,
   "LocCorner": 72,
   "LocMidrange": 33,
   "LocPaint": 57,
   "FG_RA": 69,
   "FG_ITP": 69,
   "FG_MID": 30,
   "FG_COR": 35,
   "FG_ATB": 81,
   "FT": 2,
   "Scoring": 53,
   "Passing": 33,
   "Handling": 38,
   "OReb": 53,
   "DReb": 62,
   "Block": 43,
   "Steal": 29,
   "DrawFoul": 5,
   "Defender": 48,
   "Discipline": 62,
   "BballIQ": 51,
   "FG_RA_POT": 76,
   "FG_ITP_POT": 76,
   "FG_MID_POT": 37,
   "FG_COR_POT": 42,
   "FG_ATB_POT": 88,
   "FT_POT": 9,
   "Scoring_POT": 60,
   "Passing_POT": 40,
   "Handling_POT": 45,
   "OReb_POT": 60,
   "DReb_POT": 69,
   "Block_POT": 50,
   "Steal_POT": 36,
   "DrawFoul_POT": 12,
   "Defender_POT": 55,
   "Discipline_POT": 69,
   "BballIQ_POT": 58
 },
 {
   "FirstName": "Xavier",
   "LastName": "Rathan-Mayes",
   "Position": 2,
   "Age": 23,
   "CollegeYear": 1,
   "Height": 76,
   "DisplayHeight": "6-4",
   "Weight": 208,
   "College": "Florida State",
   "Consistency": 53,
   "Greed": 37,
   "Loyalty": 61,
   "PlayForWinner": 45,
   "PlayingTime": 59,
   "Personality": 63,
   "Durability": 54,
   "WorkEthic": 64,
   "DunkRate": 49,
   "RARate": 8,
   "DriveKick": 44,
   "DriveShot": 27,
   "PostUp": 8,
   "PullUp": 34,
   "CS": 30,
   "Pass": 62,
   "LocATB": 43,
   "LocCorner": 69,
   "LocMidrange": 31,
   "LocPaint": 50,
   "FG_RA": 52,
   "FG_ITP": 52,
   "FG_MID": 34,
   "FG_COR": 39,
   "FG_ATB": 91,
   "FT": 32,
   "Scoring": 48,
   "Passing": 35,
   "Handling": 45,
   "OReb": 42,
   "DReb": 35,
   "Block": 32,
   "Steal": 53,
   "DrawFoul": 1,
   "Defender": 52,
   "Discipline": 70,
   "BballIQ": 46,
   "FG_RA_POT": 59,
   "FG_ITP_POT": 59,
   "FG_MID_POT": 41,
   "FG_COR_POT": 46,
   "FG_ATB_POT": 98,
   "FT_POT": 39,
   "Scoring_POT": 55,
   "Passing_POT": 42,
   "Handling_POT": 52,
   "OReb_POT": 49,
   "DReb_POT": 42,
   "Block_POT": 39,
   "Steal_POT": 60,
   "DrawFoul_POT": 8,
   "Defender_POT": 59,
   "Discipline_POT": 77,
   "BballIQ_POT": 53
 },
 {
   "FirstName": "Davon",
   "LastName": "Reed",
   "Position": 2,
   "Age": 22,
   "CollegeYear": 1,
   "Height": 78,
   "DisplayHeight": "6-6",
   "Weight": 210,
   "College": "Miami (FL)",
   "Consistency": 45,
   "Greed": 24,
   "Loyalty": 33,
   "PlayForWinner": 27,
   "PlayingTime": 40,
   "Personality": 59,
   "Durability": 60,
   "WorkEthic": 88,
   "DunkRate": 65,
   "RARate": 4,
   "DriveKick": 69,
   "DriveShot": 0,
   "PostUp": 33,
   "PullUp": 50,
   "CS": 34,
   "Pass": 33,
   "LocATB": 31,
   "LocCorner": 59,
   "LocMidrange": 34,
   "LocPaint": 45,
   "FG_RA": 52,
   "FG_ITP": 52,
   "FG_MID": 31,
   "FG_COR": 26,
   "FG_ATB": 86,
   "FT": 37,
   "Scoring": 43,
   "Passing": 45,
   "Handling": 55,
   "OReb": 29,
   "DReb": 40,
   "Block": 33,
   "Steal": 43,
   "DrawFoul": 4,
   "Defender": 56,
   "Discipline": 59,
   "BballIQ": 59,
   "FG_RA_POT": 59,
   "FG_ITP_POT": 59,
   "FG_MID_POT": 38,
   "FG_COR_POT": 33,
   "FG_ATB_POT": 93,
   "FT_POT": 44,
   "Scoring_POT": 50,
   "Passing_POT": 52,
   "Handling_POT": 62,
   "OReb_POT": 36,
   "DReb_POT": 47,
   "Block_POT": 40,
   "Steal_POT": 50,
   "DrawFoul_POT": 11,
   "Defender_POT": 63,
   "Discipline_POT": 66,
   "BballIQ_POT": 66
 },
 {
   "FirstName": "Devin",
   "LastName": "Robinson",
   "Position": 3,
   "Age": 22,
   "CollegeYear": 1,
   "Height": 80,
   "DisplayHeight": "6-8",
   "Weight": 200,
   "College": "Florida",
   "Consistency": 60,
   "Greed": 62,
   "Loyalty": 64,
   "PlayForWinner": 61,
   "PlayingTime": 57,
   "Personality": 66,
   "Durability": 55,
   "WorkEthic": 58,
   "DunkRate": 57,
   "RARate": 21,
   "DriveKick": 45,
   "DriveShot": 19,
   "PostUp": 47,
   "PullUp": 7,
   "CS": 33,
   "Pass": 20,
   "LocATB": 39,
   "LocCorner": 71,
   "LocMidrange": 29,
   "LocPaint": 54,
   "FG_RA": 55,
   "FG_ITP": 55,
   "FG_MID": 37,
   "FG_COR": 43,
   "FG_ATB": 84,
   "FT": 42,
   "Scoring": 56,
   "Passing": 37,
   "Handling": 49,
   "OReb": 28,
   "DReb": 41,
   "Block": 25,
   "Steal": 44,
   "DrawFoul": 2,
   "Defender": 60,
   "Discipline": 71,
   "BballIQ": 70,
   "FG_RA_POT": 62,
   "FG_ITP_POT": 62,
   "FG_MID_POT": 44,
   "FG_COR_POT": 50,
   "FG_ATB_POT": 91,
   "FT_POT": 49,
   "Scoring_POT": 63,
   "Passing_POT": 44,
   "Handling_POT": 56,
   "OReb_POT": 35,
   "DReb_POT": 48,
   "Block_POT": 32,
   "Steal_POT": 51,
   "DrawFoul_POT": 9,
   "Defender_POT": 67,
   "Discipline_POT": 78,
   "BballIQ_POT": 77
 },
 {
   "FirstName": "Corey",
   "LastName": "Sanders",
   "Position": 1,
   "Age": 23,
   "CollegeYear": 2,
   "Height": 74,
   "DisplayHeight": "6-2",
   "Weight": 176,
   "College": "Rutgers",
   "Consistency": 87,
   "Greed": 12,
   "Loyalty": 33,
   "PlayForWinner": 21,
   "PlayingTime": 27,
   "Personality": 61,
   "Durability": 67,
   "WorkEthic": 45,
   "DunkRate": 36,
   "RARate": 1,
   "DriveKick": 51,
   "DriveShot": 30,
   "PostUp": 67,
   "PullUp": 50,
   "CS": 20,
   "Pass": 13,
   "LocATB": 35,
   "LocCorner": 61,
   "LocMidrange": 33,
   "LocPaint": 56,
   "FG_RA": 55,
   "FG_ITP": 55,
   "FG_MID": 37,
   "FG_COR": 37,
   "FG_ATB": 83,
   "FT": 34,
   "Scoring": 51,
   "Passing": 27,
   "Handling": 57,
   "OReb": 43,
   "DReb": 44,
   "Block": 37,
   "Steal": 44,
   "DrawFoul": 15,
   "Defender": 50,
   "Discipline": 80,
   "BballIQ": 39,
   "FG_RA_POT": 62,
   "FG_ITP_POT": 62,
   "FG_MID_POT": 44,
   "FG_COR_POT": 44,
   "FG_ATB_POT": 90,
   "FT_POT": 41,
   "Scoring_POT": 58,
   "Passing_POT": 34,
   "Handling_POT": 64,
   "OReb_POT": 50,
   "DReb_POT": 51,
   "Block_POT": 44,
   "Steal_POT": 51,
   "DrawFoul_POT": 22,
   "Defender_POT": 57,
   "Discipline_POT": 87,
   "BballIQ_POT": 46
 },
 {
   "FirstName": "Issuf",
   "LastName": "Sanon",
   "Position": 1,
   "Age": 18,
   "CollegeYear": 3,
   "Height": 76,
   "DisplayHeight": "6-4",
   "Weight": 185,
   "College": "Ukraine",
   "Consistency": 71,
   "Greed": 19,
   "Loyalty": 45,
   "PlayForWinner": 72,
   "PlayingTime": 33,
   "Personality": 40,
   "Durability": 47,
   "WorkEthic": 77,
   "DunkRate": 75,
   "RARate": 25,
   "DriveKick": 56,
   "DriveShot": 29,
   "PostUp": 78,
   "PullUp": 50,
   "CS": 22,
   "Pass": 0,
   "LocATB": 32,
   "LocCorner": 78,
   "LocMidrange": 31,
   "LocPaint": 61,
   "FG_RA": 51,
   "FG_ITP": 51,
   "FG_MID": 32,
   "FG_COR": 33,
   "FG_ATB": 73,
   "FT": 33,
   "Scoring": 51,
   "Passing": 31,
   "Handling": 55,
   "OReb": 37,
   "DReb": 45,
   "Block": 18,
   "Steal": 62,
   "DrawFoul": 6,
   "Defender": 47,
   "Discipline": 64,
   "BballIQ": 67,
   "FG_RA_POT": 58,
   "FG_ITP_POT": 58,
   "FG_MID_POT": 39,
   "FG_COR_POT": 40,
   "FG_ATB_POT": 80,
   "FT_POT": 40,
   "Scoring_POT": 58,
   "Passing_POT": 38,
   "Handling_POT": 62,
   "OReb_POT": 44,
   "DReb_POT": 52,
   "Block_POT": 25,
   "Steal_POT": 69,
   "DrawFoul_POT": 13,
   "Defender_POT": 54,
   "Discipline_POT": 71,
   "BballIQ_POT": 74
 },
 {
   "FirstName": "Collin",
   "LastName": "Sexton",
   "Position": 1,
   "Age": 19,
   "CollegeYear": 4,
   "Height": 74,
   "DisplayHeight": "6-2",
   "Weight": 190,
   "College": "Alabama",
   "Consistency": 24,
   "Greed": 85,
   "Loyalty": 26,
   "PlayForWinner": 32,
   "PlayingTime": 19,
   "Personality": 43,
   "Durability": 26,
   "WorkEthic": 30,
   "DunkRate": 36,
   "RARate": 36,
   "DriveKick": 50,
   "DriveShot": 34,
   "PostUp": 67,
   "PullUp": 23,
   "CS": 33,
   "Pass": 0,
   "LocATB": 26,
   "LocCorner": 58,
   "LocMidrange": 32,
   "LocPaint": 60,
   "FG_RA": 62,
   "FG_ITP": 62,
   "FG_MID": 38,
   "FG_COR": 29,
   "FG_ATB": 67,
   "FT": 4,
   "Scoring": 31,
   "Passing": 35,
   "Handling": 39,
   "OReb": 35,
   "DReb": 61,
   "Block": 66,
   "Steal": 44,
   "DrawFoul": 12,
   "Defender": 32,
   "Discipline": 65,
   "BballIQ": 52,
   "FG_RA_POT": 69,
   "FG_ITP_POT": 69,
   "FG_MID_POT": 45,
   "FG_COR_POT": 36,
   "FG_ATB_POT": 74,
   "FT_POT": 11,
   "Scoring_POT": 38,
   "Passing_POT": 42,
   "Handling_POT": 46,
   "OReb_POT": 42,
   "DReb_POT": 68,
   "Block_POT": 73,
   "Steal_POT": 51,
   "DrawFoul_POT": 19,
   "Defender_POT": 39,
   "Discipline_POT": 72,
   "BballIQ_POT": 59
 },
 {
   "FirstName": "Landry",
   "LastName": "Shamet",
   "Position": 1,
   "Age": 21,
   "CollegeYear": 3,
   "Height": 77,
   "DisplayHeight": "6-5",
   "Weight": 188,
   "College": "Wichita State",
   "Consistency": 20,
   "Greed": 76,
   "Loyalty": 80,
   "PlayForWinner": 30,
   "PlayingTime": 40,
   "Personality": 39,
   "Durability": 75,
   "WorkEthic": 31,
   "DunkRate": 41,
   "RARate": 32,
   "DriveKick": 64,
   "DriveShot": 37,
   "PostUp": 36,
   "PullUp": 50,
   "CS": 64,
   "Pass": 0,
   "LocATB": 43,
   "LocCorner": 77,
   "LocMidrange": 33,
   "LocPaint": 55,
   "FG_RA": 55,
   "FG_ITP": 55,
   "FG_MID": 38,
   "FG_COR": 41,
   "FG_ATB": 84,
   "FT": 30,
   "Scoring": 51,
   "Passing": 43,
   "Handling": 35,
   "OReb": 23,
   "DReb": 44,
   "Block": 22,
   "Steal": 46,
   "DrawFoul": 6,
   "Defender": 43,
   "Discipline": 69,
   "BballIQ": 54,
   "FG_RA_POT": 62,
   "FG_ITP_POT": 62,
   "FG_MID_POT": 45,
   "FG_COR_POT": 48,
   "FG_ATB_POT": 91,
   "FT_POT": 37,
   "Scoring_POT": 58,
   "Passing_POT": 50,
   "Handling_POT": 42,
   "OReb_POT": 30,
   "DReb_POT": 51,
   "Block_POT": 29,
   "Steal_POT": 53,
   "DrawFoul_POT": 13,
   "Defender_POT": 50,
   "Discipline_POT": 76,
   "BballIQ_POT": 61
 },
 {
   "FirstName": "Ray",
   "LastName": "Spalding",
   "Position": 4,
   "Age": 21,
   "CollegeYear": 4,
   "Height": 82,
   "DisplayHeight": "6-10",
   "Weight": 210,
   "College": "Louisville",
   "Consistency": 75,
   "Greed": 92,
   "Loyalty": 43,
   "PlayForWinner": 37,
   "PlayingTime": 46,
   "Personality": 59,
   "Durability": 41,
   "WorkEthic": 80,
   "DunkRate": 37,
   "RARate": 25,
   "DriveKick": 54,
   "DriveShot": 59,
   "PostUp": 100,
   "PullUp": 50,
   "CS": 0,
   "Pass": 0,
   "LocATB": 17,
   "LocCorner": 64,
   "LocMidrange": 22,
   "LocPaint": 64,
   "FG_RA": 55,
   "FG_ITP": 55,
   "FG_MID": 38,
   "FG_COR": 41,
   "FG_ATB": 84,
   "FT": 30,
   "Scoring": 51,
   "Passing": 43,
   "Handling": 35,
   "OReb": 23,
   "DReb": 44,
   "Block": 22,
   "Steal": 46,
   "DrawFoul": 6,
   "Defender": 43,
   "Discipline": 69,
   "BballIQ": 54,
   "FG_RA_POT": 62,
   "FG_ITP_POT": 62,
   "FG_MID_POT": 45,
   "FG_COR_POT": 48,
   "FG_ATB_POT": 91,
   "FT_POT": 37,
   "Scoring_POT": 58,
   "Passing_POT": 50,
   "Handling_POT": 42,
   "OReb_POT": 30,
   "DReb_POT": 51,
   "Block_POT": 29,
   "Steal_POT": 53,
   "DrawFoul_POT": 13,
   "Defender_POT": 50,
   "Discipline_POT": 76,
   "BballIQ_POT": 61
 },
 {
   "FirstName": "Omari",
   "LastName": "Spellman",
   "Position": 4,
   "Age": 21,
   "CollegeYear": 2,
   "Height": 81,
   "DisplayHeight": "6-9",
   "Weight": 245,
   "College": "Villanova",
   "Consistency": 54,
   "Greed": 73,
   "Loyalty": 33,
   "PlayForWinner": 29,
   "PlayingTime": 56,
   "Personality": 47,
   "Durability": 80,
   "WorkEthic": 65,
   "DunkRate": 78,
   "RARate": 14,
   "DriveKick": 71,
   "DriveShot": 17,
   "PostUp": 22,
   "PullUp": 50,
   "CS": 72,
   "Pass": 6,
   "LocATB": 41,
   "LocCorner": 78,
   "LocMidrange": 38,
   "LocPaint": 50,
   "FG_RA": 70,
   "FG_ITP": 70,
   "FG_MID": 22,
   "FG_COR": 34,
   "FG_ATB": 63,
   "FT": 1,
   "Scoring": 44,
   "Passing": 24,
   "Handling": 40,
   "OReb": 60,
   "DReb": 57,
   "Block": 44,
   "Steal": 29,
   "DrawFoul": 11,
   "Defender": 56,
   "Discipline": 62,
   "BballIQ": 56,
   "FG_RA_POT": 77,
   "FG_ITP_POT": 77,
   "FG_MID_POT": 29,
   "FG_COR_POT": 41,
   "FG_ATB_POT": 70,
   "FT_POT": 8,
   "Scoring_POT": 51,
   "Passing_POT": 31,
   "Handling_POT": 47,
   "OReb_POT": 67,
   "DReb_POT": 64,
   "Block_POT": 51,
   "Steal_POT": 36,
   "DrawFoul_POT": 18,
   "Defender_POT": 63,
   "Discipline_POT": 69,
   "BballIQ_POT": 63
 },
 {
   "FirstName": "Jarred",
   "LastName": "Vanderbilt",
   "Position": 3,
   "Age": 19,
   "CollegeYear": 2,
   "Height": 81,
   "DisplayHeight": "6-9",
   "Weight": 215,
   "College": "Kentucky",
   "Consistency": 23,
   "Greed": 32,
   "Loyalty": 39,
   "PlayForWinner": 40,
   "PlayingTime": 42,
   "Personality": 50,
   "Durability": 37,
   "WorkEthic": 55,
   "DunkRate": 43,
   "RARate": 26,
   "DriveKick": 41,
   "DriveShot": 27,
   "PostUp": 77,
   "PullUp": 39,
   "CS": 23,
   "Pass": 0,
   "LocATB": 24,
   "LocCorner": 49,
   "LocMidrange": 33,
   "LocPaint": 50,
   "FG_RA": 57,
   "FG_ITP": 57,
   "FG_MID": 40,
   "FG_COR": 39,
   "FG_ATB": 87,
   "FT": 35,
   "Scoring": 43,
   "Passing": 45,
   "Handling": 61,
   "OReb": 38,
   "DReb": 56,
   "Block": 47,
   "Steal": 39,
   "DrawFoul": 4,
   "Defender": 34,
   "Discipline": 65,
   "BballIQ": 57,
   "FG_RA_POT": 64,
   "FG_ITP_POT": 64,
   "FG_MID_POT": 47,
   "FG_COR_POT": 46,
   "FG_ATB_POT": 94,
   "FT_POT": 42,
   "Scoring_POT": 50,
   "Passing_POT": 52,
   "Handling_POT": 68,
   "OReb_POT": 45,
   "DReb_POT": 63,
   "Block_POT": 54,
   "Steal_POT": 46,
   "DrawFoul_POT": 11,
   "Defender_POT": 41,
   "Discipline_POT": 72,
   "BballIQ_POT": 64
 },
 {
   "FirstName": "Yuta",
   "LastName": "Watanabe",
   "Position": 3,
   "Age": 23,
   "CollegeYear": 1,
   "Height": 81,
   "DisplayHeight": "6-9",
   "Weight": 196,
   "College": "Japan",
   "Consistency": 19,
   "Greed": 88,
   "Loyalty": 47,
   "PlayForWinner": 44,
   "PlayingTime": 39,
   "Personality": 55,
   "Durability": 89,
   "WorkEthic": 70,
   "DunkRate": 71,
   "RARate": 9,
   "DriveKick": 68,
   "DriveShot": 29,
   "PostUp": 35,
   "PullUp": 50,
   "CS": 65,
   "Pass": 0,
   "LocATB": 41,
   "LocCorner": 75,
   "LocMidrange": 36,
   "LocPaint": 57,
   "FG_RA": 57,
   "FG_ITP": 57,
   "FG_MID": 31,
   "FG_COR": 41,
   "FG_ATB": 62,
   "FT": 34,
   "Scoring": 50,
   "Passing": 32,
   "Handling": 57,
   "OReb": 43,
   "DReb": 38,
   "Block": 38,
   "Steal": 33,
   "DrawFoul": 7,
   "Defender": 59,
   "Discipline": 62,
   "BballIQ": 59,
   "FG_RA_POT": 64,
   "FG_ITP_POT": 64,
   "FG_MID_POT": 38,
   "FG_COR_POT": 48,
   "FG_ATB_POT": 69,
   "FT_POT": 41,
   "Scoring_POT": 57,
   "Passing_POT": 39,
   "Handling_POT": 64,
   "OReb_POT": 50,
   "DReb_POT": 45,
   "Block_POT": 45,
   "Steal_POT": 40,
   "DrawFoul_POT": 14,
   "Defender_POT": 66,
   "Discipline_POT": 69,
   "BballIQ_POT": 66
 },
 {
   "FirstName": "Thomas",
   "LastName": "Welsh",
   "Position": 5,
   "Age": 21,
   "CollegeYear": 1,
   "Height": 85,
   "DisplayHeight": "7-1",
   "Weight": 255,
   "College": "UCLA",
   "Consistency": 92,
   "Greed": 80,
   "Loyalty": 59,
   "PlayForWinner": 67,
   "PlayingTime": 73,
   "Personality": 60,
   "Durability": 75,
   "WorkEthic": 83,
   "DunkRate": 60,
   "RARate": 7,
   "DriveKick": 30,
   "DriveShot": 32,
   "PostUp": 35,
   "PullUp": 35,
   "CS": 40,
   "Pass": 25,
   "LocATB": 40,
   "LocCorner": 73,
   "LocMidrange": 32,
   "LocPaint": 55,
   "FG_RA": 57,
   "FG_ITP": 57,
   "FG_MID": 38,
   "FG_COR": 34,
   "FG_ATB": 64,
   "FT": 32,
   "Scoring": 25,
   "Passing": 35,
   "Handling": 45,
   "OReb": 42,
   "DReb": 50,
   "Block": 46,
   "Steal": 34,
   "DrawFoul": 11,
   "Defender": 50,
   "Discipline": 77,
   "BballIQ": 59,
   "FG_RA_POT": 64,
   "FG_ITP_POT": 64,
   "FG_MID_POT": 45,
   "FG_COR_POT": 41,
   "FG_ATB_POT": 71,
   "FT_POT": 39,
   "Scoring_POT": 32,
   "Passing_POT": 42,
   "Handling_POT": 52,
   "OReb_POT": 49,
   "DReb_POT": 57,
   "Block_POT": 53,
   "Steal_POT": 41,
   "DrawFoul_POT": 18,
   "Defender_POT": 57,
   "Discipline_POT": 84,
   "BballIQ_POT": 66
 },
 {
   "FirstName": "Robert",
   "LastName": "Williams",
   "Position": 5,
   "Age": 20,
   "CollegeYear": 1,
   "Height": 82,
   "DisplayHeight": "6-10",
   "Weight": 240,
   "College": "Texas A&M",
   "Consistency": 25,
   "Greed": 31,
   "Loyalty": 26,
   "PlayForWinner": 35,
   "PlayingTime": 25,
   "Personality": 44,
   "Durability": 61,
   "WorkEthic": 43,
   "DunkRate": 57,
   "RARate": 7,
   "DriveKick": 34,
   "DriveShot": 0,
   "PostUp": 0,
   "PullUp": 0,
   "CS": 62,
   "Pass": 38,
   "LocATB": 43,
   "LocCorner": 72,
   "LocMidrange": 34,
   "LocPaint": 50,
   "FG_RA": 51,
   "FG_ITP": 51,
   "FG_MID": 30,
   "FG_COR": 46,
   "FG_ATB": 69,
   "FT": 0,
   "Scoring": 53,
   "Passing": 32,
   "Handling": 42,
   "OReb": 61,
   "DReb": 56,
   "Block": 62,
   "Steal": 36,
   "DrawFoul": 7,
   "Defender": 51,
   "Discipline": 59,
   "BballIQ": 59,
   "FG_RA_POT": 58,
   "FG_ITP_POT": 58,
   "FG_MID_POT": 37,
   "FG_COR_POT": 53,
   "FG_ATB_POT": 76,
   "FT_POT": 7,
   "Scoring_POT": 60,
   "Passing_POT": 39,
   "Handling_POT": 49,
   "OReb_POT": 68,
   "DReb_POT": 63,
   "Block_POT": 69,
   "Steal_POT": 43,
   "DrawFoul_POT": 14,
   "Defender_POT": 58,
   "Discipline_POT": 66,
   "BballIQ_POT": 66
 },
 {
   "FirstName": "Kyle",
   "LastName": "Wiltjer",
   "Position": 4,
   "Age": 24,
   "CollegeYear": 4,
   "Height": 82,
   "DisplayHeight": "6-10",
   "Weight": 240,
   "College": "Gonzaga",
   "Consistency": 40,
   "Greed": 76,
   "Loyalty": 55,
   "PlayForWinner": 34,
   "PlayingTime": 46,
   "Personality": 60,
   "Durability": 55,
   "WorkEthic": 54,
   "DunkRate": 55,
   "RARate": 28,
   "DriveKick": 35,
   "DriveShot": 37,
   "PostUp": 56,
   "PullUp": 27,
   "CS": 0,
   "Pass": 44,
   "LocATB": 36,
   "LocCorner": 56,
   "LocMidrange": 37,
   "LocPaint": 50,
   "FG_RA": 62,
   "FG_ITP": 62,
   "FG_MID": 38,
   "FG_COR": 29,
   "FG_ATB": 67,
   "FT": 4,
   "Scoring": 31,
   "Passing": 35,
   "Handling": 39,
   "OReb": 35,
   "DReb": 61,
   "Block": 66,
   "Steal": 44,
   "DrawFoul": 12,
   "Defender": 32,
   "Discipline": 65,
   "BballIQ": 52,
   "FG_RA_POT": 69,
   "FG_ITP_POT": 69,
   "FG_MID_POT": 45,
   "FG_COR_POT": 36,
   "FG_ATB_POT": 74,
   "FT_POT": 11,
   "Scoring_POT": 38,
   "Passing_POT": 42,
   "Handling_POT": 46,
   "OReb_POT": 42,
   "DReb_POT": 68,
   "Block_POT": 73,
   "Steal_POT": 51,
   "DrawFoul_POT": 19,
   "Defender_POT": 39,
   "Discipline_POT": 72,
   "BballIQ_POT": 59
 }
]
